{".class":"MypyFile","_fullname":"torch._classes","future_import_flags":[],"is_partial_stub_package":false,"is_stub":false,"names":{".class":"SymbolTable","_ClassNamespace":{".class":"SymbolTableNode","kind":"Gdef","node":{".class":"TypeInfo","_promote":[],"abstract_attributes":[],"alt_promote":null,"bases":["types.ModuleType"],"dataclass_transform_spec":null,"declared_metaclass":null,"defn":{".class":"ClassDef","fullname":"torch._classes._ClassNamespace","name":"_ClassNamespace","type_vars":[]},"deletable_attributes":[],"flags":[],"fullname":"torch._classes._ClassNamespace","has_param_spec_type":false,"metaclass_type":null,"metadata":{},"module_name":"torch._classes","mro":["torch._classes._ClassNamespace","types.ModuleType","builtins.object"],"names":{".class":"SymbolTable","__getattr__":{".class":"SymbolTableNode","kind":"Mdef","node":{".class":"FuncDef","abstract_status":0,"arg_kinds":[0,0],"arg_names":[null,null],"dataclass_transform_spec":null,"flags":[],"fullname":"torch._classes._ClassNamespace.__getattr__","name":"__getattr__","type":null}},"__init__":{".class":"SymbolTableNode","kind":"Mdef","node":{".class":"FuncDef","abstract_status":0,"arg_kinds":[0,0],"arg_names":["self","name"],"dataclass_transform_spec":null,"flags":[],"fullname":"torch._classes._ClassNamespace.__init__","name":"__init__","type":null}},"name":{".class":"SymbolTableNode","implicit":true,"kind":"Mdef","node":{".class":"Var","flags":["is_inferred"],"fullname":"torch._classes._ClassNamespace.name","name":"name","type":{".class":"AnyType","missing_import_name":null,"source_any":null,"type_of_any":1}}}},"self_type":{".class":"TypeVarType","default":{".class":"AnyType","missing_import_name":null,"source_any":null,"type_of_any":4},"fullname":"torch._classes._ClassNamespace.Self","id":0,"name":"Self","namespace":"","upper_bound":"torch._classes._ClassNamespace","values":[],"variance":0},"slots":null,"tuple_type":null,"type_vars":[],"typeddict_type":null}},"_Classes":{".class":"SymbolTableNode","kind":"Gdef","node":{".class":"TypeInfo","_promote":[],"abstract_attributes":[],"alt_promote":null,"bases":["types.ModuleType"],"dataclass_transform_spec":null,"declared_metaclass":null,"defn":{".class":"ClassDef","fullname":"torch._classes._Classes","name":"_Classes","type_vars":[]},"deletable_attributes":[],"flags":[],"fullname":"torch._classes._Classes","has_param_spec_type":false,"metaclass_type":null,"metadata":{},"module_name":"torch._classes","mro":["torch._classes._Classes","types.ModuleType","builtins.object"],"names":{".class":"SymbolTable","__file__":{".class":"SymbolTableNode","kind":"Mdef","node":{".class":"Var","flags":["is_initialized_in_class","is_inferred","has_explicit_value"],"fullname":"torch._classes._Classes.__file__","name":"__file__","type":"builtins.str"}},"__getattr__":{".class":"SymbolTableNode","kind":"Mdef","node":{".class":"FuncDef","abstract_status":0,"arg_kinds":[0,0],"arg_names":[null,null],"dataclass_transform_spec":null,"flags":[],"fullname":"torch._classes._Classes.__getattr__","name":"__getattr__","type":null}},"__init__":{".class":"SymbolTableNode","kind":"Mdef","node":{".class":"FuncDef","abstract_status":0,"arg_kinds":[0],"arg_names":["self"],"dataclass_transform_spec":null,"flags":[],"fullname":"torch._classes._Classes.__init__","name":"__init__","type":null}},"load_library":{".class":"SymbolTableNode","kind":"Mdef","node":{".class":"FuncDef","abstract_status":0,"arg_kinds":[0,0],"arg_names":["self","path"],"dataclass_transform_spec":null,"flags":[],"fullname":"torch._classes._Classes.load_library","name":"load_library","type":null}},"loaded_libraries":{".class":"SymbolTableNode","kind":"Mdef","node":{".class":"Decorator","func":{".class":"FuncDef","abstract_status":0,"arg_kinds":[0],"arg_names":["self"],"dataclass_transform_spec":null,"flags":["is_property","is_decorated"],"fullname":"torch._classes._Classes.loaded_libraries","name":"loaded_libraries","type":null},"is_overload":false,"var":{".class":"Var","flags":["is_initialized_in_class","is_property","is_ready","is_inferred"],"fullname":"torch._classes._Classes.loaded_libraries","name":"loaded_libraries","type":{".class":"CallableType","arg_kinds":[0],"arg_names":["self"],"arg_types":["torch._classes._Classes"],"bound_args":[],"def_extras":{"first_arg":"self"},"fallback":"builtins.function","from_concatenate":false,"implicit":true,"imprecise_arg_kinds":false,"is_ellipsis_args":false,"name":"loaded_libraries of _Classes","ret_type":{".class":"AnyType","missing_import_name":null,"source_any":null,"type_of_any":1},"type_guard":null,"unpack_kwargs":false,"variables":[]}}}}},"self_type":{".class":"TypeVarType","default":{".class":"AnyType","missing_import_name":null,"source_any":null,"type_of_any":4},"fullname":"torch._classes._Classes.Self","id":0,"name":"Self","namespace":"","upper_bound":"torch._classes._Classes","values":[],"variance":0},"slots":null,"tuple_type":null,"type_vars":[],"typeddict_type":null}},"__annotations__":{".class":"SymbolTableNode","kind":"Gdef","node":{".class":"Var","flags":["is_ready"],"fullname":"torch._classes.__annotations__","name":"__annotations__","type":{".class":"Instance","args":["builtins.str",{".class":"AnyType","missing_import_name":null,"source_any":null,"type_of_any":6}],"type_ref":"builtins.dict"}}},"__doc__":{".class":"SymbolTableNode","kind":"Gdef","node":{".class":"Var","flags":["is_ready"],"fullname":"torch._classes.__doc__","name":"__doc__","type":"builtins.str"}},"__file__":{".class":"SymbolTableNode","kind":"Gdef","node":{".class":"Var","flags":["is_ready"],"fullname":"torch._classes.__file__","name":"__file__","type":"builtins.str"}},"__name__":{".class":"SymbolTableNode","kind":"Gdef","node":{".class":"Var","flags":["is_ready"],"fullname":"torch._classes.__name__","name":"__name__","type":"builtins.str"}},"__package__":{".class":"SymbolTableNode","kind":"Gdef","node":{".class":"Var","flags":["is_ready"],"fullname":"torch._classes.__package__","name":"__package__","type":"builtins.str"}},"classes":{".class":"SymbolTableNode","kind":"Gdef","node":{".class":"Var","flags":["is_inferred","has_explicit_value"],"fullname":"torch._classes.classes","name":"classes","type":"torch._classes._Classes"}},"torch":{".class":"SymbolTableNode","cross_ref":"torch","kind":"Gdef"},"types":{".class":"SymbolTableNode","cross_ref":"types","kind":"Gdef"}},"path":"/root/miniconda3/envs/dc/lib/python3.11/site-packages/torch/_classes.py"}