{".class": "MypyFile", "_fullname": "torch.jit._state", "is_partial_stub_package": false, "is_stub": false, "names": {".class": "SymbolTable", "EnabledProxy": {".class": "SymbolTableNode", "kind": "Gdef", "node": {".class": "TypeInfo", "_promote": null, "abstract_attributes": [], "bases": ["builtins.object"], "declared_metaclass": null, "defn": {".class": "ClassDef", "fullname": "torch.jit._state.EnabledProxy", "name": "EnabledProxy", "type_vars": []}, "flags": [], "fullname": "torch.jit._state.EnabledProxy", "metaclass_type": null, "metadata": {}, "module_name": "torch.jit._state", "mro": ["torch.jit._state.EnabledProxy", "builtins.object"], "names": {".class": "SymbolTable", "__bool__": {".class": "SymbolTableNode", "kind": "Mdef", "node": {".class": "FuncDef", "arg_kinds": [0], "arg_names": ["self"], "flags": [], "fullname": "torch.jit._state.EnabledProxy.__bool__", "name": "__bool__", "type": null}}, "__init__": {".class": "SymbolTableNode", "kind": "Mdef", "node": {".class": "FuncDef", "arg_kinds": [0], "arg_names": ["self"], "flags": [], "fullname": "torch.jit._state.EnabledProxy.__init__", "name": "__init__", "type": null}}, "enabled": {".class": "SymbolTableNode", "implicit": true, "kind": "Mdef", "node": {".class": "Var", "flags": [], "fullname": "torch.jit._state.EnabledProxy.enabled", "name": "enabled", "type": {".class": "AnyType", "missing_import_name": null, "source_any": null, "type_of_any": 1}}}, "parse_env": {".class": "SymbolTableNode", "kind": "Mdef", "node": {".class": "FuncDef", "arg_kinds": [0, 0, 0, 0, 0], "arg_names": ["self", "name", "default", "true_message", "false_message"], "flags": [], "fullname": "torch.jit._state.EnabledProxy.parse_env", "name": "parse_env", "type": null}}}, "tuple_type": null, "type_vars": [], "typeddict_type": null}}, "__doc__": {".class": "SymbolTableNode", "kind": "Gdef", "node": {".class": "Var", "flags": ["is_ready"], "fullname": "torch.jit._state.__doc__", "name": "__doc__", "type": "builtins.str"}}, "__file__": {".class": "SymbolTableNode", "kind": "Gdef", "node": {".class": "Var", "flags": ["is_ready"], "fullname": "torch.jit._state.__file__", "name": "__file__", "type": "builtins.str"}}, "__name__": {".class": "SymbolTableNode", "kind": "Gdef", "node": {".class": "Var", "flags": ["is_ready"], "fullname": "torch.jit._state.__name__", "name": "__name__", "type": "builtins.str"}}, "__package__": {".class": "SymbolTableNode", "kind": "Gdef", "node": {".class": "Var", "flags": ["is_ready"], "fullname": "torch.jit._state.__package__", "name": "__package__", "type": "builtins.str"}}, "_add_script_class": {".class": "SymbolTableNode", "kind": "Gdef", "node": {".class": "FuncDef", "arg_kinds": [0, 0], "arg_names": ["cls", "name"], "flags": [], "fullname": "torch.jit._state._add_script_class", "name": "_add_script_class", "type": null}}, "_enabled": {".class": "SymbolTableNode", "kind": "Gdef", "node": {".class": "Var", "flags": [], "fullname": "torch.jit._state._enabled", "name": "_enabled", "type": "torch.jit._state.EnabledProxy"}}, "_get_script_class": {".class": "SymbolTableNode", "kind": "Gdef", "node": {".class": "FuncDef", "arg_kinds": [0], "arg_names": ["name"], "flags": [], "fullname": "torch.jit._state._get_script_class", "name": "_get_script_class", "type": null}}, "_jit_caching_layer": {".class": "SymbolTableNode", "kind": "Gdef", "node": {".class": "Var", "flags": ["is_ready"], "fullname": "torch.jit._state._jit_caching_layer", "name": "_jit_caching_layer", "type": {".class": "Instance", "args": [{".class": "AnyType", "missing_import_name": null, "source_any": null, "type_of_any": 4}, {".class": "AnyType", "missing_import_name": null, "source_any": null, "type_of_any": 4}], "type_ref": "weakref.WeakKeyDictionary"}}}, "_jit_function_overload_caching": {".class": "SymbolTableNode", "kind": "Gdef", "node": {".class": "Var", "flags": ["is_ready"], "fullname": "torch.jit._state._jit_function_overload_caching", "name": "_jit_function_overload_caching", "type": {".class": "Instance", "args": [{".class": "AnyType", "missing_import_name": null, "source_any": null, "type_of_any": 4}, {".class": "AnyType", "missing_import_name": null, "source_any": null, "type_of_any": 4}], "type_ref": "weakref.WeakKeyDictionary"}}}, "_python_cu": {".class": "SymbolTableNode", "kind": "Gdef", "node": {".class": "Var", "flags": [], "fullname": "torch.jit._state._python_cu", "name": "_python_cu", "type": "torch._C.CompilationUnit"}}, "_script_classes": {".class": "SymbolTableNode", "kind": "Gdef", "node": {".class": "Var", "flags": [], "fullname": "torch.jit._state._script_classes", "name": "_script_classes", "type": {".class": "Instance", "args": [{".class": "AnyType", "missing_import_name": null, "source_any": null, "type_of_any": 1}, {".class": "AnyType", "missing_import_name": null, "source_any": null, "type_of_any": 1}], "type_ref": "builtins.dict"}}}, "_set_jit_function_cache": {".class": "SymbolTableNode", "kind": "Gdef", "node": {".class": "FuncDef", "arg_kinds": [0, 0], "arg_names": ["key", "value"], "flags": [], "fullname": "torch.jit._state._set_jit_function_cache", "name": "_set_jit_function_cache", "type": null}}, "_set_jit_overload_cache": {".class": "SymbolTableNode", "kind": "Gdef", "node": {".class": "FuncDef", "arg_kinds": [0, 0], "arg_names": ["key", "compiled_fns"], "flags": [], "fullname": "torch.jit._state._set_jit_overload_cache", "name": "_set_jit_overload_cache", "type": null}}, "_try_get_jit_cached_function": {".class": "SymbolTableNode", "kind": "Gdef", "node": {".class": "FuncDef", "arg_kinds": [0], "arg_names": ["key"], "flags": [], "fullname": "torch.jit._state._try_get_jit_cached_function", "name": "_try_get_jit_cached_function", "type": null}}, "_try_get_jit_cached_overloads": {".class": "SymbolTableNode", "kind": "Gdef", "node": {".class": "FuncDef", "arg_kinds": [0], "arg_names": ["key"], "flags": [], "fullname": "torch.jit._state._try_get_jit_cached_overloads", "name": "_try_get_jit_cached_overloads", "type": null}}, "disable": {".class": "SymbolTableNode", "kind": "Gdef", "node": {".class": "FuncDef", "arg_kinds": [], "arg_names": [], "flags": [], "fullname": "torch.jit._state.disable", "name": "disable", "type": null}}, "enable": {".class": "SymbolTableNode", "kind": "Gdef", "node": {".class": "FuncDef", "arg_kinds": [], "arg_names": [], "flags": [], "fullname": "torch.jit._state.enable", "name": "enable", "type": null}}, "os": {".class": "SymbolTableNode", "cross_ref": "os", "kind": "Gdef"}, "torch": {".class": "SymbolTableNode", "cross_ref": "torch", "kind": "Gdef"}, "weakref": {".class": "SymbolTableNode", "cross_ref": "weakref", "kind": "Gdef"}}, "path": "/usr/local/lib/python3.8/dist-packages/torch/jit/_state.py"}