{".class":"MypyFile","_fullname":"sympy.strategies.branch.core","future_import_flags":[],"is_partial_stub_package":false,"is_stub":false,"names":{".class":"SymbolTable","__annotations__":{".class":"SymbolTableNode","kind":"Gdef","node":{".class":"Var","flags":["is_ready"],"fullname":"sympy.strategies.branch.core.__annotations__","name":"__annotations__","type":{".class":"Instance","args":["builtins.str",{".class":"AnyType","missing_import_name":null,"source_any":null,"type_of_any":6}],"type_ref":"builtins.dict"}}},"__doc__":{".class":"SymbolTableNode","kind":"Gdef","node":{".class":"Var","flags":["is_ready"],"fullname":"sympy.strategies.branch.core.__doc__","name":"__doc__","type":"builtins.str"}},"__file__":{".class":"SymbolTableNode","kind":"Gdef","node":{".class":"Var","flags":["is_ready"],"fullname":"sympy.strategies.branch.core.__file__","name":"__file__","type":"builtins.str"}},"__name__":{".class":"SymbolTableNode","kind":"Gdef","node":{".class":"Var","flags":["is_ready"],"fullname":"sympy.strategies.branch.core.__name__","name":"__name__","type":"builtins.str"}},"__package__":{".class":"SymbolTableNode","kind":"Gdef","node":{".class":"Var","flags":["is_ready"],"fullname":"sympy.strategies.branch.core.__package__","name":"__package__","type":"builtins.str"}},"chain":{".class":"SymbolTableNode","kind":"Gdef","node":{".class":"FuncDef","abstract_status":0,"arg_kinds":[2],"arg_names":["brules"],"dataclass_transform_spec":null,"flags":[],"fullname":"sympy.strategies.branch.core.chain","name":"chain","type":null}},"condition":{".class":"SymbolTableNode","kind":"Gdef","node":{".class":"FuncDef","abstract_status":0,"arg_kinds":[0,0],"arg_names":["cond","brule"],"dataclass_transform_spec":null,"flags":[],"fullname":"sympy.strategies.branch.core.condition","name":"condition","type":null}},"debug":{".class":"SymbolTableNode","kind":"Gdef","node":{".class":"FuncDef","abstract_status":0,"arg_kinds":[0,1],"arg_names":["brule","file"],"dataclass_transform_spec":null,"flags":[],"fullname":"sympy.strategies.branch.core.debug","name":"debug","type":null}},"do_one":{".class":"SymbolTableNode","kind":"Gdef","node":{".class":"FuncDef","abstract_status":0,"arg_kinds":[2],"arg_names":["brules"],"dataclass_transform_spec":null,"flags":[],"fullname":"sympy.strategies.branch.core.do_one","name":"do_one","type":null}},"exhaust":{".class":"SymbolTableNode","kind":"Gdef","node":{".class":"FuncDef","abstract_status":0,"arg_kinds":[0],"arg_names":["brule"],"dataclass_transform_spec":null,"flags":[],"fullname":"sympy.strategies.branch.core.exhaust","name":"exhaust","type":null}},"identity":{".class":"SymbolTableNode","kind":"Gdef","node":{".class":"FuncDef","abstract_status":0,"arg_kinds":[0],"arg_names":["x"],"dataclass_transform_spec":null,"flags":[],"fullname":"sympy.strategies.branch.core.identity","name":"identity","type":null}},"multiplex":{".class":"SymbolTableNode","kind":"Gdef","node":{".class":"FuncDef","abstract_status":0,"arg_kinds":[2],"arg_names":["brules"],"dataclass_transform_spec":null,"flags":[],"fullname":"sympy.strategies.branch.core.multiplex","name":"multiplex","type":null}},"notempty":{".class":"SymbolTableNode","kind":"Gdef","node":{".class":"FuncDef","abstract_status":0,"arg_kinds":[0],"arg_names":["brule"],"dataclass_transform_spec":null,"flags":[],"fullname":"sympy.strategies.branch.core.notempty","name":"notempty","type":null}},"onaction":{".class":"SymbolTableNode","kind":"Gdef","node":{".class":"FuncDef","abstract_status":0,"arg_kinds":[0,0],"arg_names":["brule","fn"],"dataclass_transform_spec":null,"flags":[],"fullname":"sympy.strategies.branch.core.onaction","name":"onaction","type":null}},"sfilter":{".class":"SymbolTableNode","kind":"Gdef","node":{".class":"FuncDef","abstract_status":0,"arg_kinds":[0,0],"arg_names":["pred","brule"],"dataclass_transform_spec":null,"flags":[],"fullname":"sympy.strategies.branch.core.sfilter","name":"sfilter","type":null}},"yieldify":{".class":"SymbolTableNode","kind":"Gdef","node":{".class":"FuncDef","abstract_status":0,"arg_kinds":[0],"arg_names":["rl"],"dataclass_transform_spec":null,"flags":[],"fullname":"sympy.strategies.branch.core.yieldify","name":"yieldify","type":null}}},"path":"/root/miniconda3/envs/dc/lib/python3.11/site-packages/sympy/strategies/branch/core.py"}