{".class":"MypyFile","_fullname":"sympy.printing.pretty.pretty","future_import_flags":[],"is_partial_stub_package":false,"is_stub":false,"names":{".class":"SymbolTable","Add":{".class":"SymbolTableNode","cross_ref":"sympy.core.add.Add","kind":"Gdef"},"Function":{".class":"SymbolTableNode","cross_ref":"sympy.core.function.Function","kind":"Gdef"},"Mul":{".class":"SymbolTableNode","cross_ref":"sympy.core.mul.Mul","kind":"Gdef"},"Number":{".class":"SymbolTableNode","cross_ref":"sympy.core.numbers.Number","kind":"Gdef"},"PRECEDENCE":{".class":"SymbolTableNode","cross_ref":"sympy.printing.precedence.PRECEDENCE","kind":"Gdef"},"Pow":{".class":"SymbolTableNode","cross_ref":"sympy.core.power.Pow","kind":"Gdef"},"PrettyPrinter":{".class":"SymbolTableNode","kind":"Gdef","node":{".class":"TypeInfo","_promote":[],"abstract_attributes":[],"alt_promote":null,"bases":["sympy.printing.printer.Printer"],"dataclass_transform_spec":null,"declared_metaclass":null,"defn":{".class":"ClassDef","fullname":"sympy.printing.pretty.pretty.PrettyPrinter","name":"PrettyPrinter","type_vars":[]},"deletable_attributes":[],"flags":[],"fullname":"sympy.printing.pretty.pretty.PrettyPrinter","has_param_spec_type":false,"metaclass_type":null,"metadata":{},"module_name":"sympy.printing.pretty.pretty","mro":["sympy.printing.pretty.pretty.PrettyPrinter","sympy.printing.printer.Printer","builtins.object"],"names":{".class":"SymbolTable","__init__":{".class":"SymbolTableNode","kind":"Mdef","node":{".class":"FuncDef","abstract_status":0,"arg_kinds":[0,1],"arg_names":["self","settings"],"dataclass_transform_spec":null,"flags":[],"fullname":"sympy.printing.pretty.pretty.PrettyPrinter.__init__","name":"__init__","type":null}},"__print_Boolean":{".class":"SymbolTableNode","kind":"Mdef","node":{".class":"FuncDef","abstract_status":0,"arg_kinds":[0,0,0,1],"arg_names":["self","e","char","sort"],"dataclass_transform_spec":null,"flags":[],"fullname":"sympy.printing.pretty.pretty.PrettyPrinter.__print_Boolean","name":"__print_Boolean","type":null}},"__print_SumProduct_Limits":{".class":"SymbolTableNode","kind":"Mdef","node":{".class":"FuncDef","abstract_status":0,"arg_kinds":[0,0],"arg_names":["self","lim"],"dataclass_transform_spec":null,"flags":[],"fullname":"sympy.printing.pretty.pretty.PrettyPrinter.__print_SumProduct_Limits","name":"__print_SumProduct_Limits","type":null}},"__print_numer_denom":{".class":"SymbolTableNode","kind":"Mdef","node":{".class":"FuncDef","abstract_status":0,"arg_kinds":[0,0,0],"arg_names":["self","p","q"],"dataclass_transform_spec":null,"flags":[],"fullname":"sympy.printing.pretty.pretty.PrettyPrinter.__print_numer_denom","name":"__print_numer_denom","type":null}},"_default_settings":{".class":"SymbolTableNode","kind":"Mdef","node":{".class":"Var","flags":["is_initialized_in_class","is_inferred","has_explicit_value"],"fullname":"sympy.printing.pretty.pretty.PrettyPrinter._default_settings","name":"_default_settings","type":{".class":"Instance","args":["builtins.str",{".class":"AnyType","missing_import_name":null,"source_any":{".class":"AnyType","missing_import_name":null,"source_any":null,"type_of_any":2},"type_of_any":7}],"type_ref":"builtins.dict"}}},"_helper_print_function":{".class":"SymbolTableNode","kind":"Mdef","node":{".class":"FuncDef","abstract_status":0,"arg_kinds":[0,0,0,1,1,1,1,1,1],"arg_names":["self","func","args","sort","func_name","delimiter","elementwise","left","right"],"dataclass_transform_spec":null,"flags":[],"fullname":"sympy.printing.pretty.pretty.PrettyPrinter._helper_print_function","name":"_helper_print_function","type":null}},"_hprint_vec":{".class":"SymbolTableNode","kind":"Mdef","node":{".class":"FuncDef","abstract_status":0,"arg_kinds":[0,0],"arg_names":["self","v"],"dataclass_transform_spec":null,"flags":[],"fullname":"sympy.printing.pretty.pretty.PrettyPrinter._hprint_vec","name":"_hprint_vec","type":null}},"_hprint_vseparator":{".class":"SymbolTableNode","kind":"Mdef","node":{".class":"FuncDef","abstract_status":0,"arg_kinds":[0,0,0,1,1,1,1],"arg_names":["self","p1","p2","left","right","delimiter","ifascii_nougly"],"dataclass_transform_spec":null,"flags":[],"fullname":"sympy.printing.pretty.pretty.PrettyPrinter._hprint_vseparator","name":"_hprint_vseparator","type":null}},"_print_Abs":{".class":"SymbolTableNode","kind":"Mdef","node":{".class":"FuncDef","abstract_status":0,"arg_kinds":[0,0],"arg_names":["self","e"],"dataclass_transform_spec":null,"flags":[],"fullname":"sympy.printing.pretty.pretty.PrettyPrinter._print_Abs","name":"_print_Abs","type":null}},"_print_AccumulationBounds":{".class":"SymbolTableNode","kind":"Mdef","node":{".class":"FuncDef","abstract_status":0,"arg_kinds":[0,0],"arg_names":["self","i"],"dataclass_transform_spec":null,"flags":[],"fullname":"sympy.printing.pretty.pretty.PrettyPrinter._print_AccumulationBounds","name":"_print_AccumulationBounds","type":null}},"_print_Add":{".class":"SymbolTableNode","kind":"Mdef","node":{".class":"FuncDef","abstract_status":0,"arg_kinds":[0,0,1],"arg_names":["self","expr","order"],"dataclass_transform_spec":null,"flags":[],"fullname":"sympy.printing.pretty.pretty.PrettyPrinter._print_Add","name":"_print_Add","type":null}},"_print_Adjoint":{".class":"SymbolTableNode","kind":"Mdef","node":{".class":"FuncDef","abstract_status":0,"arg_kinds":[0,0],"arg_names":["self","expr"],"dataclass_transform_spec":null,"flags":[],"fullname":"sympy.printing.pretty.pretty.PrettyPrinter._print_Adjoint","name":"_print_Adjoint","type":null}},"_print_AlgebraicNumber":{".class":"SymbolTableNode","kind":"Mdef","node":{".class":"FuncDef","abstract_status":0,"arg_kinds":[0,0],"arg_names":["self","expr"],"dataclass_transform_spec":null,"flags":[],"fullname":"sympy.printing.pretty.pretty.PrettyPrinter._print_AlgebraicNumber","name":"_print_AlgebraicNumber","type":null}},"_print_And":{".class":"SymbolTableNode","kind":"Mdef","node":{".class":"FuncDef","abstract_status":0,"arg_kinds":[0,0],"arg_names":["self","e"],"dataclass_transform_spec":null,"flags":[],"fullname":"sympy.printing.pretty.pretty.PrettyPrinter._print_And","name":"_print_And","type":null}},"_print_AssignmentBase":{".class":"SymbolTableNode","kind":"Mdef","node":{".class":"FuncDef","abstract_status":0,"arg_kinds":[0,0],"arg_names":["self","e"],"dataclass_transform_spec":null,"flags":[],"fullname":"sympy.printing.pretty.pretty.PrettyPrinter._print_AssignmentBase","name":"_print_AssignmentBase","type":null}},"_print_Atom":{".class":"SymbolTableNode","kind":"Mdef","node":{".class":"FuncDef","abstract_status":0,"arg_kinds":[0,0],"arg_names":["self","e"],"dataclass_transform_spec":null,"flags":[],"fullname":"sympy.printing.pretty.pretty.PrettyPrinter._print_Atom","name":"_print_Atom","type":null}},"_print_BaseScalarField":{".class":"SymbolTableNode","kind":"Mdef","node":{".class":"FuncDef","abstract_status":0,"arg_kinds":[0,0],"arg_names":["self","field"],"dataclass_transform_spec":null,"flags":[],"fullname":"sympy.printing.pretty.pretty.PrettyPrinter._print_BaseScalarField","name":"_print_BaseScalarField","type":null}},"_print_BaseVectorField":{".class":"SymbolTableNode","kind":"Mdef","node":{".class":"FuncDef","abstract_status":0,"arg_kinds":[0,0],"arg_names":["self","field"],"dataclass_transform_spec":null,"flags":[],"fullname":"sympy.printing.pretty.pretty.PrettyPrinter._print_BaseVectorField","name":"_print_BaseVectorField","type":null}},"_print_BasisDependent":{".class":"SymbolTableNode","kind":"Mdef","node":{".class":"FuncDef","abstract_status":0,"arg_kinds":[0,0],"arg_names":["self","expr"],"dataclass_transform_spec":null,"flags":[],"fullname":"sympy.printing.pretty.pretty.PrettyPrinter._print_BasisDependent","name":"_print_BasisDependent","type":null}},"_print_BlockMatrix":{".class":"SymbolTableNode","kind":"Mdef","node":{".class":"FuncDef","abstract_status":0,"arg_kinds":[0,0],"arg_names":["self","B"],"dataclass_transform_spec":null,"flags":[],"fullname":"sympy.printing.pretty.pretty.PrettyPrinter._print_BlockMatrix","name":"_print_BlockMatrix","type":null}},"_print_Catalan":{".class":"SymbolTableNode","kind":"Mdef","node":{".class":"FuncDef","abstract_status":0,"arg_kinds":[0,0],"arg_names":["self","expr"],"dataclass_transform_spec":null,"flags":[],"fullname":"sympy.printing.pretty.pretty.PrettyPrinter._print_Catalan","name":"_print_Catalan","type":null}},"_print_Category":{".class":"SymbolTableNode","kind":"Mdef","node":{".class":"FuncDef","abstract_status":0,"arg_kinds":[0,0],"arg_names":["self","category"],"dataclass_transform_spec":null,"flags":[],"fullname":"sympy.printing.pretty.pretty.PrettyPrinter._print_Category","name":"_print_Category","type":null}},"_print_Chi":{".class":"SymbolTableNode","kind":"Mdef","node":{".class":"FuncDef","abstract_status":0,"arg_kinds":[0,0],"arg_names":["self","e"],"dataclass_transform_spec":null,"flags":[],"fullname":"sympy.printing.pretty.pretty.PrettyPrinter._print_Chi","name":"_print_Chi","type":null}},"_print_Complement":{".class":"SymbolTableNode","kind":"Mdef","node":{".class":"FuncDef","abstract_status":0,"arg_kinds":[0,0],"arg_names":["self","u"],"dataclass_transform_spec":null,"flags":[],"fullname":"sympy.printing.pretty.pretty.PrettyPrinter._print_Complement","name":"_print_Complement","type":null}},"_print_ComplexField":{".class":"SymbolTableNode","kind":"Mdef","node":{".class":"FuncDef","abstract_status":0,"arg_kinds":[0,0],"arg_names":["self","domain"],"dataclass_transform_spec":null,"flags":[],"fullname":"sympy.printing.pretty.pretty.PrettyPrinter._print_ComplexField","name":"_print_ComplexField","type":null}},"_print_ComplexRegion":{".class":"SymbolTableNode","kind":"Mdef","node":{".class":"FuncDef","abstract_status":0,"arg_kinds":[0,0],"arg_names":["self","ts"],"dataclass_transform_spec":null,"flags":[],"fullname":"sympy.printing.pretty.pretty.PrettyPrinter._print_ComplexRegion","name":"_print_ComplexRegion","type":null}},"_print_ComplexRootOf":{".class":"SymbolTableNode","kind":"Mdef","node":{".class":"FuncDef","abstract_status":0,"arg_kinds":[0,0],"arg_names":["self","expr"],"dataclass_transform_spec":null,"flags":[],"fullname":"sympy.printing.pretty.pretty.PrettyPrinter._print_ComplexRootOf","name":"_print_ComplexRootOf","type":null}},"_print_Complexes":{".class":"SymbolTableNode","kind":"Mdef","node":{".class":"Var","flags":["is_initialized_in_class","is_inferred","has_explicit_value"],"fullname":"sympy.printing.pretty.pretty.PrettyPrinter._print_Complexes","name":"_print_Complexes","type":{".class":"CallableType","arg_kinds":[0,0],"arg_names":["self","e"],"arg_types":["sympy.printing.pretty.pretty.PrettyPrinter",{".class":"AnyType","missing_import_name":null,"source_any":null,"type_of_any":1}],"bound_args":[],"def_extras":{"first_arg":"self"},"fallback":"builtins.function","from_concatenate":false,"implicit":true,"imprecise_arg_kinds":false,"is_ellipsis_args":false,"name":null,"ret_type":{".class":"AnyType","missing_import_name":null,"source_any":null,"type_of_any":1},"type_guard":null,"unpack_kwargs":false,"variables":[]}}},"_print_CompositeMorphism":{".class":"SymbolTableNode","kind":"Mdef","node":{".class":"FuncDef","abstract_status":0,"arg_kinds":[0,0],"arg_names":["self","morphism"],"dataclass_transform_spec":null,"flags":[],"fullname":"sympy.printing.pretty.pretty.PrettyPrinter._print_CompositeMorphism","name":"_print_CompositeMorphism","type":null}},"_print_ConditionSet":{".class":"SymbolTableNode","kind":"Mdef","node":{".class":"FuncDef","abstract_status":0,"arg_kinds":[0,0],"arg_names":["self","ts"],"dataclass_transform_spec":null,"flags":[],"fullname":"sympy.printing.pretty.pretty.PrettyPrinter._print_ConditionSet","name":"_print_ConditionSet","type":null}},"_print_Contains":{".class":"SymbolTableNode","kind":"Mdef","node":{".class":"FuncDef","abstract_status":0,"arg_kinds":[0,0],"arg_names":["self","e"],"dataclass_transform_spec":null,"flags":[],"fullname":"sympy.printing.pretty.pretty.PrettyPrinter._print_Contains","name":"_print_Contains","type":null}},"_print_CoordSystem":{".class":"SymbolTableNode","kind":"Mdef","node":{".class":"FuncDef","abstract_status":0,"arg_kinds":[0,0],"arg_names":["self","coords"],"dataclass_transform_spec":null,"flags":[],"fullname":"sympy.printing.pretty.pretty.PrettyPrinter._print_CoordSystem","name":"_print_CoordSystem","type":null}},"_print_Covariance":{".class":"SymbolTableNode","kind":"Mdef","node":{".class":"FuncDef","abstract_status":0,"arg_kinds":[0,0],"arg_names":["self","e"],"dataclass_transform_spec":null,"flags":[],"fullname":"sympy.printing.pretty.pretty.PrettyPrinter._print_Covariance","name":"_print_Covariance","type":null}},"_print_Cross":{".class":"SymbolTableNode","kind":"Mdef","node":{".class":"FuncDef","abstract_status":0,"arg_kinds":[0,0],"arg_names":["self","e"],"dataclass_transform_spec":null,"flags":[],"fullname":"sympy.printing.pretty.pretty.PrettyPrinter._print_Cross","name":"_print_Cross","type":null}},"_print_Curl":{".class":"SymbolTableNode","kind":"Mdef","node":{".class":"FuncDef","abstract_status":0,"arg_kinds":[0,0],"arg_names":["self","e"],"dataclass_transform_spec":null,"flags":[],"fullname":"sympy.printing.pretty.pretty.PrettyPrinter._print_Curl","name":"_print_Curl","type":null}},"_print_Cycle":{".class":"SymbolTableNode","kind":"Mdef","node":{".class":"FuncDef","abstract_status":0,"arg_kinds":[0,0],"arg_names":["self","dc"],"dataclass_transform_spec":null,"flags":[],"fullname":"sympy.printing.pretty.pretty.PrettyPrinter._print_Cycle","name":"_print_Cycle","type":null}},"_print_DMF":{".class":"SymbolTableNode","kind":"Mdef","node":{".class":"FuncDef","abstract_status":0,"arg_kinds":[0,0],"arg_names":["self","p"],"dataclass_transform_spec":null,"flags":[],"fullname":"sympy.printing.pretty.pretty.PrettyPrinter._print_DMF","name":"_print_DMF","type":null}},"_print_DMP":{".class":"SymbolTableNode","kind":"Mdef","node":{".class":"FuncDef","abstract_status":0,"arg_kinds":[0,0],"arg_names":["self","p"],"dataclass_transform_spec":null,"flags":[],"fullname":"sympy.printing.pretty.pretty.PrettyPrinter._print_DMP","name":"_print_DMP","type":null}},"_print_Derivative":{".class":"SymbolTableNode","kind":"Mdef","node":{".class":"FuncDef","abstract_status":0,"arg_kinds":[0,0],"arg_names":["self","deriv"],"dataclass_transform_spec":null,"flags":[],"fullname":"sympy.printing.pretty.pretty.PrettyPrinter._print_Derivative","name":"_print_Derivative","type":null}},"_print_Determinant":{".class":"SymbolTableNode","kind":"Mdef","node":{".class":"FuncDef","abstract_status":0,"arg_kinds":[0,0],"arg_names":["self","e"],"dataclass_transform_spec":null,"flags":[],"fullname":"sympy.printing.pretty.pretty.PrettyPrinter._print_Determinant","name":"_print_Determinant","type":null}},"_print_Diagram":{".class":"SymbolTableNode","kind":"Mdef","node":{".class":"FuncDef","abstract_status":0,"arg_kinds":[0,0],"arg_names":["self","diagram"],"dataclass_transform_spec":null,"flags":[],"fullname":"sympy.printing.pretty.pretty.PrettyPrinter._print_Diagram","name":"_print_Diagram","type":null}},"_print_DiagramGrid":{".class":"SymbolTableNode","kind":"Mdef","node":{".class":"FuncDef","abstract_status":0,"arg_kinds":[0,0],"arg_names":["self","grid"],"dataclass_transform_spec":null,"flags":[],"fullname":"sympy.printing.pretty.pretty.PrettyPrinter._print_DiagramGrid","name":"_print_DiagramGrid","type":null}},"_print_Dict":{".class":"SymbolTableNode","kind":"Mdef","node":{".class":"FuncDef","abstract_status":0,"arg_kinds":[0,0],"arg_names":["self","d"],"dataclass_transform_spec":null,"flags":[],"fullname":"sympy.printing.pretty.pretty.PrettyPrinter._print_Dict","name":"_print_Dict","type":null}},"_print_Differential":{".class":"SymbolTableNode","kind":"Mdef","node":{".class":"FuncDef","abstract_status":0,"arg_kinds":[0,0],"arg_names":["self","diff"],"dataclass_transform_spec":null,"flags":[],"fullname":"sympy.printing.pretty.pretty.PrettyPrinter._print_Differential","name":"_print_Differential","type":null}},"_print_DiracDelta":{".class":"SymbolTableNode","kind":"Mdef","node":{".class":"FuncDef","abstract_status":0,"arg_kinds":[0,0],"arg_names":["self","e"],"dataclass_transform_spec":null,"flags":[],"fullname":"sympy.printing.pretty.pretty.PrettyPrinter._print_DiracDelta","name":"_print_DiracDelta","type":null}},"_print_Divergence":{".class":"SymbolTableNode","kind":"Mdef","node":{".class":"FuncDef","abstract_status":0,"arg_kinds":[0,0],"arg_names":["self","e"],"dataclass_transform_spec":null,"flags":[],"fullname":"sympy.printing.pretty.pretty.PrettyPrinter._print_Divergence","name":"_print_Divergence","type":null}},"_print_Dot":{".class":"SymbolTableNode","kind":"Mdef","node":{".class":"FuncDef","abstract_status":0,"arg_kinds":[0,0],"arg_names":["self","e"],"dataclass_transform_spec":null,"flags":[],"fullname":"sympy.printing.pretty.pretty.PrettyPrinter._print_Dot","name":"_print_Dot","type":null}},"_print_DotProduct":{".class":"SymbolTableNode","kind":"Mdef","node":{".class":"FuncDef","abstract_status":0,"arg_kinds":[0,0],"arg_names":["self","expr"],"dataclass_transform_spec":null,"flags":[],"fullname":"sympy.printing.pretty.pretty.PrettyPrinter._print_DotProduct","name":"_print_DotProduct","type":null}},"_print_ElementwiseApplyFunction":{".class":"SymbolTableNode","kind":"Mdef","node":{".class":"FuncDef","abstract_status":0,"arg_kinds":[0,0],"arg_names":["self","e"],"dataclass_transform_spec":null,"flags":[],"fullname":"sympy.printing.pretty.pretty.PrettyPrinter._print_ElementwiseApplyFunction","name":"_print_ElementwiseApplyFunction","type":null}},"_print_EmptySequence":{".class":"SymbolTableNode","kind":"Mdef","node":{".class":"Var","flags":["is_initialized_in_class","is_inferred","has_explicit_value"],"fullname":"sympy.printing.pretty.pretty.PrettyPrinter._print_EmptySequence","name":"_print_EmptySequence","type":{".class":"CallableType","arg_kinds":[0,0],"arg_names":["self","e"],"arg_types":["sympy.printing.pretty.pretty.PrettyPrinter",{".class":"AnyType","missing_import_name":null,"source_any":null,"type_of_any":1}],"bound_args":[],"def_extras":{"first_arg":"self"},"fallback":"builtins.function","from_concatenate":false,"implicit":true,"imprecise_arg_kinds":false,"is_ellipsis_args":false,"name":null,"ret_type":{".class":"AnyType","missing_import_name":null,"source_any":null,"type_of_any":1},"type_guard":null,"unpack_kwargs":false,"variables":[]}}},"_print_EmptySet":{".class":"SymbolTableNode","kind":"Mdef","node":{".class":"Var","flags":["is_initialized_in_class","is_inferred","has_explicit_value"],"fullname":"sympy.printing.pretty.pretty.PrettyPrinter._print_EmptySet","name":"_print_EmptySet","type":{".class":"CallableType","arg_kinds":[0,0],"arg_names":["self","e"],"arg_types":["sympy.printing.pretty.pretty.PrettyPrinter",{".class":"AnyType","missing_import_name":null,"source_any":null,"type_of_any":1}],"bound_args":[],"def_extras":{"first_arg":"self"},"fallback":"builtins.function","from_concatenate":false,"implicit":true,"imprecise_arg_kinds":false,"is_ellipsis_args":false,"name":null,"ret_type":{".class":"AnyType","missing_import_name":null,"source_any":null,"type_of_any":1},"type_guard":null,"unpack_kwargs":false,"variables":[]}}},"_print_Equivalent":{".class":"SymbolTableNode","kind":"Mdef","node":{".class":"FuncDef","abstract_status":0,"arg_kinds":[0,0,1],"arg_names":["self","e","altchar"],"dataclass_transform_spec":null,"flags":[],"fullname":"sympy.printing.pretty.pretty.PrettyPrinter._print_Equivalent","name":"_print_Equivalent","type":null}},"_print_EulerGamma":{".class":"SymbolTableNode","kind":"Mdef","node":{".class":"FuncDef","abstract_status":0,"arg_kinds":[0,0],"arg_names":["self","expr"],"dataclass_transform_spec":null,"flags":[],"fullname":"sympy.printing.pretty.pretty.PrettyPrinter._print_EulerGamma","name":"_print_EulerGamma","type":null}},"_print_Exp1":{".class":"SymbolTableNode","kind":"Mdef","node":{".class":"FuncDef","abstract_status":0,"arg_kinds":[0,0],"arg_names":["self","e"],"dataclass_transform_spec":null,"flags":[],"fullname":"sympy.printing.pretty.pretty.PrettyPrinter._print_Exp1","name":"_print_Exp1","type":null}},"_print_ExpBase":{".class":"SymbolTableNode","kind":"Mdef","node":{".class":"FuncDef","abstract_status":0,"arg_kinds":[0,0],"arg_names":["self","e"],"dataclass_transform_spec":null,"flags":[],"fullname":"sympy.printing.pretty.pretty.PrettyPrinter._print_ExpBase","name":"_print_ExpBase","type":null}},"_print_Expectation":{".class":"SymbolTableNode","kind":"Mdef","node":{".class":"FuncDef","abstract_status":0,"arg_kinds":[0,0],"arg_names":["self","e"],"dataclass_transform_spec":null,"flags":[],"fullname":"sympy.printing.pretty.pretty.PrettyPrinter._print_Expectation","name":"_print_Expectation","type":null}},"_print_Feedback":{".class":"SymbolTableNode","kind":"Mdef","node":{".class":"FuncDef","abstract_status":0,"arg_kinds":[0,0],"arg_names":["self","expr"],"dataclass_transform_spec":null,"flags":[],"fullname":"sympy.printing.pretty.pretty.PrettyPrinter._print_Feedback","name":"_print_Feedback","type":null}},"_print_FiniteField":{".class":"SymbolTableNode","kind":"Mdef","node":{".class":"FuncDef","abstract_status":0,"arg_kinds":[0,0],"arg_names":["self","expr"],"dataclass_transform_spec":null,"flags":[],"fullname":"sympy.printing.pretty.pretty.PrettyPrinter._print_FiniteField","name":"_print_FiniteField","type":null}},"_print_FiniteSet":{".class":"SymbolTableNode","kind":"Mdef","node":{".class":"FuncDef","abstract_status":0,"arg_kinds":[0,0],"arg_names":["self","s"],"dataclass_transform_spec":null,"flags":[],"fullname":"sympy.printing.pretty.pretty.PrettyPrinter._print_FiniteSet","name":"_print_FiniteSet","type":null}},"_print_Float":{".class":"SymbolTableNode","kind":"Mdef","node":{".class":"FuncDef","abstract_status":0,"arg_kinds":[0,0],"arg_names":["self","e"],"dataclass_transform_spec":null,"flags":[],"fullname":"sympy.printing.pretty.pretty.PrettyPrinter._print_Float","name":"_print_Float","type":null}},"_print_FormalPowerSeries":{".class":"SymbolTableNode","kind":"Mdef","node":{".class":"FuncDef","abstract_status":0,"arg_kinds":[0,0],"arg_names":["self","s"],"dataclass_transform_spec":null,"flags":[],"fullname":"sympy.printing.pretty.pretty.PrettyPrinter._print_FormalPowerSeries","name":"_print_FormalPowerSeries","type":null}},"_print_FourierSeries":{".class":"SymbolTableNode","kind":"Mdef","node":{".class":"FuncDef","abstract_status":0,"arg_kinds":[0,0],"arg_names":["self","s"],"dataclass_transform_spec":null,"flags":[],"fullname":"sympy.printing.pretty.pretty.PrettyPrinter._print_FourierSeries","name":"_print_FourierSeries","type":null}},"_print_FracElement":{".class":"SymbolTableNode","kind":"Mdef","node":{".class":"FuncDef","abstract_status":0,"arg_kinds":[0,0],"arg_names":["self","frac"],"dataclass_transform_spec":null,"flags":[],"fullname":"sympy.printing.pretty.pretty.PrettyPrinter._print_FracElement","name":"_print_FracElement","type":null}},"_print_FracField":{".class":"SymbolTableNode","kind":"Mdef","node":{".class":"FuncDef","abstract_status":0,"arg_kinds":[0,0],"arg_names":["self","field"],"dataclass_transform_spec":null,"flags":[],"fullname":"sympy.printing.pretty.pretty.PrettyPrinter._print_FracField","name":"_print_FracField","type":null}},"_print_Fraction":{".class":"SymbolTableNode","kind":"Mdef","node":{".class":"FuncDef","abstract_status":0,"arg_kinds":[0,0],"arg_names":["self","expr"],"dataclass_transform_spec":null,"flags":[],"fullname":"sympy.printing.pretty.pretty.PrettyPrinter._print_Fraction","name":"_print_Fraction","type":null}},"_print_FractionField":{".class":"SymbolTableNode","kind":"Mdef","node":{".class":"FuncDef","abstract_status":0,"arg_kinds":[0,0],"arg_names":["self","expr"],"dataclass_transform_spec":null,"flags":[],"fullname":"sympy.printing.pretty.pretty.PrettyPrinter._print_FractionField","name":"_print_FractionField","type":null}},"_print_FreeGroupElement":{".class":"SymbolTableNode","kind":"Mdef","node":{".class":"FuncDef","abstract_status":0,"arg_kinds":[0,0],"arg_names":["self","elm"],"dataclass_transform_spec":null,"flags":[],"fullname":"sympy.printing.pretty.pretty.PrettyPrinter._print_FreeGroupElement","name":"_print_FreeGroupElement","type":null}},"_print_FreeModule":{".class":"SymbolTableNode","kind":"Mdef","node":{".class":"FuncDef","abstract_status":0,"arg_kinds":[0,0],"arg_names":["self","M"],"dataclass_transform_spec":null,"flags":[],"fullname":"sympy.printing.pretty.pretty.PrettyPrinter._print_FreeModule","name":"_print_FreeModule","type":null}},"_print_FreeModuleElement":{".class":"SymbolTableNode","kind":"Mdef","node":{".class":"FuncDef","abstract_status":0,"arg_kinds":[0,0],"arg_names":["self","m"],"dataclass_transform_spec":null,"flags":[],"fullname":"sympy.printing.pretty.pretty.PrettyPrinter._print_FreeModuleElement","name":"_print_FreeModuleElement","type":null}},"_print_Function":{".class":"SymbolTableNode","kind":"Mdef","node":{".class":"FuncDef","abstract_status":0,"arg_kinds":[0,0,1,1,1,1],"arg_names":["self","e","sort","func_name","left","right"],"dataclass_transform_spec":null,"flags":[],"fullname":"sympy.printing.pretty.pretty.PrettyPrinter._print_Function","name":"_print_Function","type":null}},"_print_FunctionClass":{".class":"SymbolTableNode","kind":"Mdef","node":{".class":"FuncDef","abstract_status":0,"arg_kinds":[0,0],"arg_names":["self","expr"],"dataclass_transform_spec":null,"flags":[],"fullname":"sympy.printing.pretty.pretty.PrettyPrinter._print_FunctionClass","name":"_print_FunctionClass","type":null}},"_print_FunctionMatrix":{".class":"SymbolTableNode","kind":"Mdef","node":{".class":"FuncDef","abstract_status":0,"arg_kinds":[0,0],"arg_names":["self","X"],"dataclass_transform_spec":null,"flags":[],"fullname":"sympy.printing.pretty.pretty.PrettyPrinter._print_FunctionMatrix","name":"_print_FunctionMatrix","type":null}},"_print_GeometryEntity":{".class":"SymbolTableNode","kind":"Mdef","node":{".class":"FuncDef","abstract_status":0,"arg_kinds":[0,0],"arg_names":["self","expr"],"dataclass_transform_spec":null,"flags":[],"fullname":"sympy.printing.pretty.pretty.PrettyPrinter._print_GeometryEntity","name":"_print_GeometryEntity","type":null}},"_print_GoldenRatio":{".class":"SymbolTableNode","kind":"Mdef","node":{".class":"FuncDef","abstract_status":0,"arg_kinds":[0,0],"arg_names":["self","expr"],"dataclass_transform_spec":null,"flags":[],"fullname":"sympy.printing.pretty.pretty.PrettyPrinter._print_GoldenRatio","name":"_print_GoldenRatio","type":null}},"_print_Gradient":{".class":"SymbolTableNode","kind":"Mdef","node":{".class":"FuncDef","abstract_status":0,"arg_kinds":[0,0],"arg_names":["self","e"],"dataclass_transform_spec":null,"flags":[],"fullname":"sympy.printing.pretty.pretty.PrettyPrinter._print_Gradient","name":"_print_Gradient","type":null}},"_print_GroebnerBasis":{".class":"SymbolTableNode","kind":"Mdef","node":{".class":"FuncDef","abstract_status":0,"arg_kinds":[0,0],"arg_names":["self","basis"],"dataclass_transform_spec":null,"flags":[],"fullname":"sympy.printing.pretty.pretty.PrettyPrinter._print_GroebnerBasis","name":"_print_GroebnerBasis","type":null}},"_print_HadamardPower":{".class":"SymbolTableNode","kind":"Mdef","node":{".class":"FuncDef","abstract_status":0,"arg_kinds":[0,0],"arg_names":["self","expr"],"dataclass_transform_spec":null,"flags":[],"fullname":"sympy.printing.pretty.pretty.PrettyPrinter._print_HadamardPower","name":"_print_HadamardPower","type":null}},"_print_HadamardProduct":{".class":"SymbolTableNode","kind":"Mdef","node":{".class":"FuncDef","abstract_status":0,"arg_kinds":[0,0],"arg_names":["self","expr"],"dataclass_transform_spec":null,"flags":[],"fullname":"sympy.printing.pretty.pretty.PrettyPrinter._print_HadamardProduct","name":"_print_HadamardProduct","type":null}},"_print_Heaviside":{".class":"SymbolTableNode","kind":"Mdef","node":{".class":"FuncDef","abstract_status":0,"arg_kinds":[0,0],"arg_names":["self","e"],"dataclass_transform_spec":null,"flags":[],"fullname":"sympy.printing.pretty.pretty.PrettyPrinter._print_Heaviside","name":"_print_Heaviside","type":null}},"_print_ITE":{".class":"SymbolTableNode","kind":"Mdef","node":{".class":"FuncDef","abstract_status":0,"arg_kinds":[0,0],"arg_names":["self","ite"],"dataclass_transform_spec":null,"flags":[],"fullname":"sympy.printing.pretty.pretty.PrettyPrinter._print_ITE","name":"_print_ITE","type":null}},"_print_Identity":{".class":"SymbolTableNode","kind":"Mdef","node":{".class":"FuncDef","abstract_status":0,"arg_kinds":[0,0],"arg_names":["self","expr"],"dataclass_transform_spec":null,"flags":[],"fullname":"sympy.printing.pretty.pretty.PrettyPrinter._print_Identity","name":"_print_Identity","type":null}},"_print_IdentityMorphism":{".class":"SymbolTableNode","kind":"Mdef","node":{".class":"FuncDef","abstract_status":0,"arg_kinds":[0,0],"arg_names":["self","morphism"],"dataclass_transform_spec":null,"flags":[],"fullname":"sympy.printing.pretty.pretty.PrettyPrinter._print_IdentityMorphism","name":"_print_IdentityMorphism","type":null}},"_print_ImageSet":{".class":"SymbolTableNode","kind":"Mdef","node":{".class":"FuncDef","abstract_status":0,"arg_kinds":[0,0],"arg_names":["self","ts"],"dataclass_transform_spec":null,"flags":[],"fullname":"sympy.printing.pretty.pretty.PrettyPrinter._print_ImageSet","name":"_print_ImageSet","type":null}},"_print_Implies":{".class":"SymbolTableNode","kind":"Mdef","node":{".class":"FuncDef","abstract_status":0,"arg_kinds":[0,0,1],"arg_names":["self","e","altchar"],"dataclass_transform_spec":null,"flags":[],"fullname":"sympy.printing.pretty.pretty.PrettyPrinter._print_Implies","name":"_print_Implies","type":null}},"_print_Infinity":{".class":"SymbolTableNode","kind":"Mdef","node":{".class":"Var","flags":["is_initialized_in_class","is_inferred","has_explicit_value"],"fullname":"sympy.printing.pretty.pretty.PrettyPrinter._print_Infinity","name":"_print_Infinity","type":{".class":"CallableType","arg_kinds":[0,0],"arg_names":["self","e"],"arg_types":["sympy.printing.pretty.pretty.PrettyPrinter",{".class":"AnyType","missing_import_name":null,"source_any":null,"type_of_any":1}],"bound_args":[],"def_extras":{"first_arg":"self"},"fallback":"builtins.function","from_concatenate":false,"implicit":true,"imprecise_arg_kinds":false,"is_ellipsis_args":false,"name":null,"ret_type":{".class":"AnyType","missing_import_name":null,"source_any":null,"type_of_any":1},"type_guard":null,"unpack_kwargs":false,"variables":[]}}},"_print_IntegerRing":{".class":"SymbolTableNode","kind":"Mdef","node":{".class":"FuncDef","abstract_status":0,"arg_kinds":[0,0],"arg_names":["self","expr"],"dataclass_transform_spec":null,"flags":[],"fullname":"sympy.printing.pretty.pretty.PrettyPrinter._print_IntegerRing","name":"_print_IntegerRing","type":null}},"_print_Integers":{".class":"SymbolTableNode","kind":"Mdef","node":{".class":"Var","flags":["is_initialized_in_class","is_inferred","has_explicit_value"],"fullname":"sympy.printing.pretty.pretty.PrettyPrinter._print_Integers","name":"_print_Integers","type":{".class":"CallableType","arg_kinds":[0,0],"arg_names":["self","e"],"arg_types":["sympy.printing.pretty.pretty.PrettyPrinter",{".class":"AnyType","missing_import_name":null,"source_any":null,"type_of_any":1}],"bound_args":[],"def_extras":{"first_arg":"self"},"fallback":"builtins.function","from_concatenate":false,"implicit":true,"imprecise_arg_kinds":false,"is_ellipsis_args":false,"name":null,"ret_type":{".class":"AnyType","missing_import_name":null,"source_any":null,"type_of_any":1},"type_guard":null,"unpack_kwargs":false,"variables":[]}}},"_print_Integral":{".class":"SymbolTableNode","kind":"Mdef","node":{".class":"FuncDef","abstract_status":0,"arg_kinds":[0,0],"arg_names":["self","integral"],"dataclass_transform_spec":null,"flags":[],"fullname":"sympy.printing.pretty.pretty.PrettyPrinter._print_Integral","name":"_print_Integral","type":null}},"_print_Intersection":{".class":"SymbolTableNode","kind":"Mdef","node":{".class":"FuncDef","abstract_status":0,"arg_kinds":[0,0],"arg_names":["self","u"],"dataclass_transform_spec":null,"flags":[],"fullname":"sympy.printing.pretty.pretty.PrettyPrinter._print_Intersection","name":"_print_Intersection","type":null}},"_print_Interval":{".class":"SymbolTableNode","kind":"Mdef","node":{".class":"FuncDef","abstract_status":0,"arg_kinds":[0,0],"arg_names":["self","i"],"dataclass_transform_spec":null,"flags":[],"fullname":"sympy.printing.pretty.pretty.PrettyPrinter._print_Interval","name":"_print_Interval","type":null}},"_print_KroneckerDelta":{".class":"SymbolTableNode","kind":"Mdef","node":{".class":"FuncDef","abstract_status":0,"arg_kinds":[0,0],"arg_names":["self","e"],"dataclass_transform_spec":null,"flags":[],"fullname":"sympy.printing.pretty.pretty.PrettyPrinter._print_KroneckerDelta","name":"_print_KroneckerDelta","type":null}},"_print_KroneckerProduct":{".class":"SymbolTableNode","kind":"Mdef","node":{".class":"FuncDef","abstract_status":0,"arg_kinds":[0,0],"arg_names":["self","expr"],"dataclass_transform_spec":null,"flags":[],"fullname":"sympy.printing.pretty.pretty.PrettyPrinter._print_KroneckerProduct","name":"_print_KroneckerProduct","type":null}},"_print_Lambda":{".class":"SymbolTableNode","kind":"Mdef","node":{".class":"FuncDef","abstract_status":0,"arg_kinds":[0,0],"arg_names":["self","e"],"dataclass_transform_spec":null,"flags":[],"fullname":"sympy.printing.pretty.pretty.PrettyPrinter._print_Lambda","name":"_print_Lambda","type":null}},"_print_LambertW":{".class":"SymbolTableNode","kind":"Mdef","node":{".class":"FuncDef","abstract_status":0,"arg_kinds":[0,0],"arg_names":["self","e"],"dataclass_transform_spec":null,"flags":[],"fullname":"sympy.printing.pretty.pretty.PrettyPrinter._print_LambertW","name":"_print_LambertW","type":null}},"_print_Laplacian":{".class":"SymbolTableNode","kind":"Mdef","node":{".class":"FuncDef","abstract_status":0,"arg_kinds":[0,0],"arg_names":["self","e"],"dataclass_transform_spec":null,"flags":[],"fullname":"sympy.printing.pretty.pretty.PrettyPrinter._print_Laplacian","name":"_print_Laplacian","type":null}},"_print_Limit":{".class":"SymbolTableNode","kind":"Mdef","node":{".class":"FuncDef","abstract_status":0,"arg_kinds":[0,0],"arg_names":["self","l"],"dataclass_transform_spec":null,"flags":[],"fullname":"sympy.printing.pretty.pretty.PrettyPrinter._print_Limit","name":"_print_Limit","type":null}},"_print_MIMOFeedback":{".class":"SymbolTableNode","kind":"Mdef","node":{".class":"FuncDef","abstract_status":0,"arg_kinds":[0,0],"arg_names":["self","expr"],"dataclass_transform_spec":null,"flags":[],"fullname":"sympy.printing.pretty.pretty.PrettyPrinter._print_MIMOFeedback","name":"_print_MIMOFeedback","type":null}},"_print_MIMOParallel":{".class":"SymbolTableNode","kind":"Mdef","node":{".class":"FuncDef","abstract_status":0,"arg_kinds":[0,0],"arg_names":["self","expr"],"dataclass_transform_spec":null,"flags":[],"fullname":"sympy.printing.pretty.pretty.PrettyPrinter._print_MIMOParallel","name":"_print_MIMOParallel","type":null}},"_print_MIMOSeries":{".class":"SymbolTableNode","kind":"Mdef","node":{".class":"FuncDef","abstract_status":0,"arg_kinds":[0,0],"arg_names":["self","expr"],"dataclass_transform_spec":null,"flags":[],"fullname":"sympy.printing.pretty.pretty.PrettyPrinter._print_MIMOSeries","name":"_print_MIMOSeries","type":null}},"_print_Manifold":{".class":"SymbolTableNode","kind":"Mdef","node":{".class":"FuncDef","abstract_status":0,"arg_kinds":[0,0],"arg_names":["self","manifold"],"dataclass_transform_spec":null,"flags":[],"fullname":"sympy.printing.pretty.pretty.PrettyPrinter._print_Manifold","name":"_print_Manifold","type":null}},"_print_MatAdd":{".class":"SymbolTableNode","kind":"Mdef","node":{".class":"FuncDef","abstract_status":0,"arg_kinds":[0,0],"arg_names":["self","expr"],"dataclass_transform_spec":null,"flags":[],"fullname":"sympy.printing.pretty.pretty.PrettyPrinter._print_MatAdd","name":"_print_MatAdd","type":null}},"_print_MatMul":{".class":"SymbolTableNode","kind":"Mdef","node":{".class":"FuncDef","abstract_status":0,"arg_kinds":[0,0],"arg_names":["self","expr"],"dataclass_transform_spec":null,"flags":[],"fullname":"sympy.printing.pretty.pretty.PrettyPrinter._print_MatMul","name":"_print_MatMul","type":null}},"_print_MatPow":{".class":"SymbolTableNode","kind":"Mdef","node":{".class":"FuncDef","abstract_status":0,"arg_kinds":[0,0],"arg_names":["self","expr"],"dataclass_transform_spec":null,"flags":[],"fullname":"sympy.printing.pretty.pretty.PrettyPrinter._print_MatPow","name":"_print_MatPow","type":null}},"_print_MatrixBase":{".class":"SymbolTableNode","kind":"Mdef","node":{".class":"FuncDef","abstract_status":0,"arg_kinds":[0,0,1,1],"arg_names":["self","e","lparens","rparens"],"dataclass_transform_spec":null,"flags":[],"fullname":"sympy.printing.pretty.pretty.PrettyPrinter._print_MatrixBase","name":"_print_MatrixBase","type":null}},"_print_MatrixElement":{".class":"SymbolTableNode","kind":"Mdef","node":{".class":"FuncDef","abstract_status":0,"arg_kinds":[0,0],"arg_names":["self","expr"],"dataclass_transform_spec":null,"flags":[],"fullname":"sympy.printing.pretty.pretty.PrettyPrinter._print_MatrixElement","name":"_print_MatrixElement","type":null}},"_print_MatrixHomomorphism":{".class":"SymbolTableNode","kind":"Mdef","node":{".class":"FuncDef","abstract_status":0,"arg_kinds":[0,0],"arg_names":["self","h"],"dataclass_transform_spec":null,"flags":[],"fullname":"sympy.printing.pretty.pretty.PrettyPrinter._print_MatrixHomomorphism","name":"_print_MatrixHomomorphism","type":null}},"_print_MatrixSlice":{".class":"SymbolTableNode","kind":"Mdef","node":{".class":"FuncDef","abstract_status":0,"arg_kinds":[0,0],"arg_names":["self","m"],"dataclass_transform_spec":null,"flags":[],"fullname":"sympy.printing.pretty.pretty.PrettyPrinter._print_MatrixSlice","name":"_print_MatrixSlice","type":null}},"_print_MatrixSymbol":{".class":"SymbolTableNode","kind":"Mdef","node":{".class":"FuncDef","abstract_status":0,"arg_kinds":[0,0],"arg_names":["self","e"],"dataclass_transform_spec":null,"flags":[],"fullname":"sympy.printing.pretty.pretty.PrettyPrinter._print_MatrixSymbol","name":"_print_MatrixSymbol","type":null}},"_print_Mod":{".class":"SymbolTableNode","kind":"Mdef","node":{".class":"FuncDef","abstract_status":0,"arg_kinds":[0,0],"arg_names":["self","expr"],"dataclass_transform_spec":null,"flags":[],"fullname":"sympy.printing.pretty.pretty.PrettyPrinter._print_Mod","name":"_print_Mod","type":null}},"_print_ModuleImplementedIdeal":{".class":"SymbolTableNode","kind":"Mdef","node":{".class":"FuncDef","abstract_status":0,"arg_kinds":[0,0],"arg_names":["self","M"],"dataclass_transform_spec":null,"flags":[],"fullname":"sympy.printing.pretty.pretty.PrettyPrinter._print_ModuleImplementedIdeal","name":"_print_ModuleImplementedIdeal","type":null}},"_print_Morphism":{".class":"SymbolTableNode","kind":"Mdef","node":{".class":"FuncDef","abstract_status":0,"arg_kinds":[0,0],"arg_names":["self","morphism"],"dataclass_transform_spec":null,"flags":[],"fullname":"sympy.printing.pretty.pretty.PrettyPrinter._print_Morphism","name":"_print_Morphism","type":null}},"_print_Mul":{".class":"SymbolTableNode","kind":"Mdef","node":{".class":"FuncDef","abstract_status":0,"arg_kinds":[0,0],"arg_names":["self","product"],"dataclass_transform_spec":null,"flags":[],"fullname":"sympy.printing.pretty.pretty.PrettyPrinter._print_Mul","name":"_print_Mul","type":null}},"_print_NDimArray":{".class":"SymbolTableNode","kind":"Mdef","node":{".class":"FuncDef","abstract_status":0,"arg_kinds":[0,0],"arg_names":["self","expr"],"dataclass_transform_spec":null,"flags":[],"fullname":"sympy.printing.pretty.pretty.PrettyPrinter._print_NDimArray","name":"_print_NDimArray","type":null}},"_print_NamedMorphism":{".class":"SymbolTableNode","kind":"Mdef","node":{".class":"FuncDef","abstract_status":0,"arg_kinds":[0,0],"arg_names":["self","morphism"],"dataclass_transform_spec":null,"flags":[],"fullname":"sympy.printing.pretty.pretty.PrettyPrinter._print_NamedMorphism","name":"_print_NamedMorphism","type":null}},"_print_Nand":{".class":"SymbolTableNode","kind":"Mdef","node":{".class":"FuncDef","abstract_status":0,"arg_kinds":[0,0],"arg_names":["self","e"],"dataclass_transform_spec":null,"flags":[],"fullname":"sympy.printing.pretty.pretty.PrettyPrinter._print_Nand","name":"_print_Nand","type":null}},"_print_Naturals":{".class":"SymbolTableNode","kind":"Mdef","node":{".class":"Var","flags":["is_initialized_in_class","is_inferred","has_explicit_value"],"fullname":"sympy.printing.pretty.pretty.PrettyPrinter._print_Naturals","name":"_print_Naturals","type":{".class":"CallableType","arg_kinds":[0,0],"arg_names":["self","e"],"arg_types":["sympy.printing.pretty.pretty.PrettyPrinter",{".class":"AnyType","missing_import_name":null,"source_any":null,"type_of_any":1}],"bound_args":[],"def_extras":{"first_arg":"self"},"fallback":"builtins.function","from_concatenate":false,"implicit":true,"imprecise_arg_kinds":false,"is_ellipsis_args":false,"name":null,"ret_type":{".class":"AnyType","missing_import_name":null,"source_any":null,"type_of_any":1},"type_guard":null,"unpack_kwargs":false,"variables":[]}}},"_print_Naturals0":{".class":"SymbolTableNode","kind":"Mdef","node":{".class":"Var","flags":["is_initialized_in_class","is_inferred","has_explicit_value"],"fullname":"sympy.printing.pretty.pretty.PrettyPrinter._print_Naturals0","name":"_print_Naturals0","type":{".class":"CallableType","arg_kinds":[0,0],"arg_names":["self","e"],"arg_types":["sympy.printing.pretty.pretty.PrettyPrinter",{".class":"AnyType","missing_import_name":null,"source_any":null,"type_of_any":1}],"bound_args":[],"def_extras":{"first_arg":"self"},"fallback":"builtins.function","from_concatenate":false,"implicit":true,"imprecise_arg_kinds":false,"is_ellipsis_args":false,"name":null,"ret_type":{".class":"AnyType","missing_import_name":null,"source_any":null,"type_of_any":1},"type_guard":null,"unpack_kwargs":false,"variables":[]}}},"_print_NegativeInfinity":{".class":"SymbolTableNode","kind":"Mdef","node":{".class":"Var","flags":["is_initialized_in_class","is_inferred","has_explicit_value"],"fullname":"sympy.printing.pretty.pretty.PrettyPrinter._print_NegativeInfinity","name":"_print_NegativeInfinity","type":{".class":"CallableType","arg_kinds":[0,0],"arg_names":["self","e"],"arg_types":["sympy.printing.pretty.pretty.PrettyPrinter",{".class":"AnyType","missing_import_name":null,"source_any":null,"type_of_any":1}],"bound_args":[],"def_extras":{"first_arg":"self"},"fallback":"builtins.function","from_concatenate":false,"implicit":true,"imprecise_arg_kinds":false,"is_ellipsis_args":false,"name":null,"ret_type":{".class":"AnyType","missing_import_name":null,"source_any":null,"type_of_any":1},"type_guard":null,"unpack_kwargs":false,"variables":[]}}},"_print_Nor":{".class":"SymbolTableNode","kind":"Mdef","node":{".class":"FuncDef","abstract_status":0,"arg_kinds":[0,0],"arg_names":["self","e"],"dataclass_transform_spec":null,"flags":[],"fullname":"sympy.printing.pretty.pretty.PrettyPrinter._print_Nor","name":"_print_Nor","type":null}},"_print_Not":{".class":"SymbolTableNode","kind":"Mdef","node":{".class":"FuncDef","abstract_status":0,"arg_kinds":[0,0],"arg_names":["self","e"],"dataclass_transform_spec":null,"flags":[],"fullname":"sympy.printing.pretty.pretty.PrettyPrinter._print_Not","name":"_print_Not","type":null}},"_print_Object":{".class":"SymbolTableNode","kind":"Mdef","node":{".class":"FuncDef","abstract_status":0,"arg_kinds":[0,0],"arg_names":["self","object"],"dataclass_transform_spec":null,"flags":[],"fullname":"sympy.printing.pretty.pretty.PrettyPrinter._print_Object","name":"_print_Object","type":null}},"_print_OneMatrix":{".class":"SymbolTableNode","kind":"Mdef","node":{".class":"FuncDef","abstract_status":0,"arg_kinds":[0,0],"arg_names":["self","expr"],"dataclass_transform_spec":null,"flags":[],"fullname":"sympy.printing.pretty.pretty.PrettyPrinter._print_OneMatrix","name":"_print_OneMatrix","type":null}},"_print_Or":{".class":"SymbolTableNode","kind":"Mdef","node":{".class":"FuncDef","abstract_status":0,"arg_kinds":[0,0],"arg_names":["self","e"],"dataclass_transform_spec":null,"flags":[],"fullname":"sympy.printing.pretty.pretty.PrettyPrinter._print_Or","name":"_print_Or","type":null}},"_print_Order":{".class":"SymbolTableNode","kind":"Mdef","node":{".class":"FuncDef","abstract_status":0,"arg_kinds":[0,0],"arg_names":["self","expr"],"dataclass_transform_spec":null,"flags":[],"fullname":"sympy.printing.pretty.pretty.PrettyPrinter._print_Order","name":"_print_Order","type":null}},"_print_Parallel":{".class":"SymbolTableNode","kind":"Mdef","node":{".class":"FuncDef","abstract_status":0,"arg_kinds":[0,0],"arg_names":["self","expr"],"dataclass_transform_spec":null,"flags":[],"fullname":"sympy.printing.pretty.pretty.PrettyPrinter._print_Parallel","name":"_print_Parallel","type":null}},"_print_PartialDerivative":{".class":"SymbolTableNode","kind":"Mdef","node":{".class":"FuncDef","abstract_status":0,"arg_kinds":[0,0],"arg_names":["self","deriv"],"dataclass_transform_spec":null,"flags":[],"fullname":"sympy.printing.pretty.pretty.PrettyPrinter._print_PartialDerivative","name":"_print_PartialDerivative","type":null}},"_print_Patch":{".class":"SymbolTableNode","kind":"Mdef","node":{".class":"FuncDef","abstract_status":0,"arg_kinds":[0,0],"arg_names":["self","patch"],"dataclass_transform_spec":null,"flags":[],"fullname":"sympy.printing.pretty.pretty.PrettyPrinter._print_Patch","name":"_print_Patch","type":null}},"_print_Permutation":{".class":"SymbolTableNode","kind":"Mdef","node":{".class":"FuncDef","abstract_status":0,"arg_kinds":[0,0],"arg_names":["self","expr"],"dataclass_transform_spec":null,"flags":[],"fullname":"sympy.printing.pretty.pretty.PrettyPrinter._print_Permutation","name":"_print_Permutation","type":null}},"_print_Piecewise":{".class":"SymbolTableNode","kind":"Mdef","node":{".class":"FuncDef","abstract_status":0,"arg_kinds":[0,0],"arg_names":["self","pexpr"],"dataclass_transform_spec":null,"flags":[],"fullname":"sympy.printing.pretty.pretty.PrettyPrinter._print_Piecewise","name":"_print_Piecewise","type":null}},"_print_PolyElement":{".class":"SymbolTableNode","kind":"Mdef","node":{".class":"FuncDef","abstract_status":0,"arg_kinds":[0,0],"arg_names":["self","poly"],"dataclass_transform_spec":null,"flags":[],"fullname":"sympy.printing.pretty.pretty.PrettyPrinter._print_PolyElement","name":"_print_PolyElement","type":null}},"_print_PolyRing":{".class":"SymbolTableNode","kind":"Mdef","node":{".class":"FuncDef","abstract_status":0,"arg_kinds":[0,0],"arg_names":["self","ring"],"dataclass_transform_spec":null,"flags":[],"fullname":"sympy.printing.pretty.pretty.PrettyPrinter._print_PolyRing","name":"_print_PolyRing","type":null}},"_print_PolynomialRing":{".class":"SymbolTableNode","kind":"Mdef","node":{".class":"FuncDef","abstract_status":0,"arg_kinds":[0,0],"arg_names":["self","expr"],"dataclass_transform_spec":null,"flags":[],"fullname":"sympy.printing.pretty.pretty.PrettyPrinter._print_PolynomialRing","name":"_print_PolynomialRing","type":null}},"_print_PolynomialRingBase":{".class":"SymbolTableNode","kind":"Mdef","node":{".class":"FuncDef","abstract_status":0,"arg_kinds":[0,0],"arg_names":["self","expr"],"dataclass_transform_spec":null,"flags":[],"fullname":"sympy.printing.pretty.pretty.PrettyPrinter._print_PolynomialRingBase","name":"_print_PolynomialRingBase","type":null}},"_print_Pow":{".class":"SymbolTableNode","kind":"Mdef","node":{".class":"FuncDef","abstract_status":0,"arg_kinds":[0,0],"arg_names":["self","power"],"dataclass_transform_spec":null,"flags":[],"fullname":"sympy.printing.pretty.pretty.PrettyPrinter._print_Pow","name":"_print_Pow","type":null}},"_print_Probability":{".class":"SymbolTableNode","kind":"Mdef","node":{".class":"FuncDef","abstract_status":0,"arg_kinds":[0,0],"arg_names":["self","e"],"dataclass_transform_spec":null,"flags":[],"fullname":"sympy.printing.pretty.pretty.PrettyPrinter._print_Probability","name":"_print_Probability","type":null}},"_print_Product":{".class":"SymbolTableNode","kind":"Mdef","node":{".class":"FuncDef","abstract_status":0,"arg_kinds":[0,0],"arg_names":["self","expr"],"dataclass_transform_spec":null,"flags":[],"fullname":"sympy.printing.pretty.pretty.PrettyPrinter._print_Product","name":"_print_Product","type":null}},"_print_ProductSet":{".class":"SymbolTableNode","kind":"Mdef","node":{".class":"FuncDef","abstract_status":0,"arg_kinds":[0,0],"arg_names":["self","p"],"dataclass_transform_spec":null,"flags":[],"fullname":"sympy.printing.pretty.pretty.PrettyPrinter._print_ProductSet","name":"_print_ProductSet","type":null}},"_print_Quantity":{".class":"SymbolTableNode","kind":"Mdef","node":{".class":"FuncDef","abstract_status":0,"arg_kinds":[0,0],"arg_names":["self","e"],"dataclass_transform_spec":null,"flags":[],"fullname":"sympy.printing.pretty.pretty.PrettyPrinter._print_Quantity","name":"_print_Quantity","type":null}},"_print_QuotientModule":{".class":"SymbolTableNode","kind":"Mdef","node":{".class":"FuncDef","abstract_status":0,"arg_kinds":[0,0],"arg_names":["self","M"],"dataclass_transform_spec":null,"flags":[],"fullname":"sympy.printing.pretty.pretty.PrettyPrinter._print_QuotientModule","name":"_print_QuotientModule","type":null}},"_print_QuotientModuleElement":{".class":"SymbolTableNode","kind":"Mdef","node":{".class":"FuncDef","abstract_status":0,"arg_kinds":[0,0],"arg_names":["self","m"],"dataclass_transform_spec":null,"flags":[],"fullname":"sympy.printing.pretty.pretty.PrettyPrinter._print_QuotientModuleElement","name":"_print_QuotientModuleElement","type":null}},"_print_QuotientRing":{".class":"SymbolTableNode","kind":"Mdef","node":{".class":"FuncDef","abstract_status":0,"arg_kinds":[0,0],"arg_names":["self","R"],"dataclass_transform_spec":null,"flags":[],"fullname":"sympy.printing.pretty.pretty.PrettyPrinter._print_QuotientRing","name":"_print_QuotientRing","type":null}},"_print_QuotientRingElement":{".class":"SymbolTableNode","kind":"Mdef","node":{".class":"FuncDef","abstract_status":0,"arg_kinds":[0,0],"arg_names":["self","R"],"dataclass_transform_spec":null,"flags":[],"fullname":"sympy.printing.pretty.pretty.PrettyPrinter._print_QuotientRingElement","name":"_print_QuotientRingElement","type":null}},"_print_RandomDomain":{".class":"SymbolTableNode","kind":"Mdef","node":{".class":"FuncDef","abstract_status":0,"arg_kinds":[0,0],"arg_names":["self","d"],"dataclass_transform_spec":null,"flags":[],"fullname":"sympy.printing.pretty.pretty.PrettyPrinter._print_RandomDomain","name":"_print_RandomDomain","type":null}},"_print_RandomSymbol":{".class":"SymbolTableNode","kind":"Mdef","node":{".class":"Var","flags":["is_initialized_in_class","is_inferred","has_explicit_value"],"fullname":"sympy.printing.pretty.pretty.PrettyPrinter._print_RandomSymbol","name":"_print_RandomSymbol","type":{".class":"CallableType","arg_kinds":[0,0,1],"arg_names":["self","e","bold_name"],"arg_types":["sympy.printing.pretty.pretty.PrettyPrinter",{".class":"AnyType","missing_import_name":null,"source_any":null,"type_of_any":1},{".class":"AnyType","missing_import_name":null,"source_any":null,"type_of_any":1}],"bound_args":[],"def_extras":{"first_arg":"self"},"fallback":"builtins.function","from_concatenate":false,"implicit":true,"imprecise_arg_kinds":false,"is_ellipsis_args":false,"name":null,"ret_type":{".class":"AnyType","missing_import_name":null,"source_any":null,"type_of_any":1},"type_guard":null,"unpack_kwargs":false,"variables":[]}}},"_print_Range":{".class":"SymbolTableNode","kind":"Mdef","node":{".class":"FuncDef","abstract_status":0,"arg_kinds":[0,0],"arg_names":["self","s"],"dataclass_transform_spec":null,"flags":[],"fullname":"sympy.printing.pretty.pretty.PrettyPrinter._print_Range","name":"_print_Range","type":null}},"_print_Rational":{".class":"SymbolTableNode","kind":"Mdef","node":{".class":"FuncDef","abstract_status":0,"arg_kinds":[0,0],"arg_names":["self","expr"],"dataclass_transform_spec":null,"flags":[],"fullname":"sympy.printing.pretty.pretty.PrettyPrinter._print_Rational","name":"_print_Rational","type":null}},"_print_RationalField":{".class":"SymbolTableNode","kind":"Mdef","node":{".class":"FuncDef","abstract_status":0,"arg_kinds":[0,0],"arg_names":["self","expr"],"dataclass_transform_spec":null,"flags":[],"fullname":"sympy.printing.pretty.pretty.PrettyPrinter._print_RationalField","name":"_print_RationalField","type":null}},"_print_Rationals":{".class":"SymbolTableNode","kind":"Mdef","node":{".class":"Var","flags":["is_initialized_in_class","is_inferred","has_explicit_value"],"fullname":"sympy.printing.pretty.pretty.PrettyPrinter._print_Rationals","name":"_print_Rationals","type":{".class":"CallableType","arg_kinds":[0,0],"arg_names":["self","e"],"arg_types":["sympy.printing.pretty.pretty.PrettyPrinter",{".class":"AnyType","missing_import_name":null,"source_any":null,"type_of_any":1}],"bound_args":[],"def_extras":{"first_arg":"self"},"fallback":"builtins.function","from_concatenate":false,"implicit":true,"imprecise_arg_kinds":false,"is_ellipsis_args":false,"name":null,"ret_type":{".class":"AnyType","missing_import_name":null,"source_any":null,"type_of_any":1},"type_guard":null,"unpack_kwargs":false,"variables":[]}}},"_print_RealField":{".class":"SymbolTableNode","kind":"Mdef","node":{".class":"FuncDef","abstract_status":0,"arg_kinds":[0,0],"arg_names":["self","domain"],"dataclass_transform_spec":null,"flags":[],"fullname":"sympy.printing.pretty.pretty.PrettyPrinter._print_RealField","name":"_print_RealField","type":null}},"_print_Reals":{".class":"SymbolTableNode","kind":"Mdef","node":{".class":"FuncDef","abstract_status":0,"arg_kinds":[0,0],"arg_names":["self","e"],"dataclass_transform_spec":null,"flags":[],"fullname":"sympy.printing.pretty.pretty.PrettyPrinter._print_Reals","name":"_print_Reals","type":null}},"_print_Relational":{".class":"SymbolTableNode","kind":"Mdef","node":{".class":"FuncDef","abstract_status":0,"arg_kinds":[0,0],"arg_names":["self","e"],"dataclass_transform_spec":null,"flags":[],"fullname":"sympy.printing.pretty.pretty.PrettyPrinter._print_Relational","name":"_print_Relational","type":null}},"_print_RootSum":{".class":"SymbolTableNode","kind":"Mdef","node":{".class":"FuncDef","abstract_status":0,"arg_kinds":[0,0],"arg_names":["self","expr"],"dataclass_transform_spec":null,"flags":[],"fullname":"sympy.printing.pretty.pretty.PrettyPrinter._print_RootSum","name":"_print_RootSum","type":null}},"_print_SeqAdd":{".class":"SymbolTableNode","kind":"Mdef","node":{".class":"Var","flags":["is_initialized_in_class","is_inferred","has_explicit_value"],"fullname":"sympy.printing.pretty.pretty.PrettyPrinter._print_SeqAdd","name":"_print_SeqAdd","type":{".class":"CallableType","arg_kinds":[0,0],"arg_names":["self","s"],"arg_types":["sympy.printing.pretty.pretty.PrettyPrinter",{".class":"AnyType","missing_import_name":null,"source_any":null,"type_of_any":1}],"bound_args":[],"def_extras":{"first_arg":"self"},"fallback":"builtins.function","from_concatenate":false,"implicit":true,"imprecise_arg_kinds":false,"is_ellipsis_args":false,"name":null,"ret_type":{".class":"AnyType","missing_import_name":null,"source_any":null,"type_of_any":1},"type_guard":null,"unpack_kwargs":false,"variables":[]}}},"_print_SeqFormula":{".class":"SymbolTableNode","kind":"Mdef","node":{".class":"FuncDef","abstract_status":0,"arg_kinds":[0,0],"arg_names":["self","s"],"dataclass_transform_spec":null,"flags":[],"fullname":"sympy.printing.pretty.pretty.PrettyPrinter._print_SeqFormula","name":"_print_SeqFormula","type":null}},"_print_SeqMul":{".class":"SymbolTableNode","kind":"Mdef","node":{".class":"Var","flags":["is_initialized_in_class","is_inferred","has_explicit_value"],"fullname":"sympy.printing.pretty.pretty.PrettyPrinter._print_SeqMul","name":"_print_SeqMul","type":{".class":"CallableType","arg_kinds":[0,0],"arg_names":["self","s"],"arg_types":["sympy.printing.pretty.pretty.PrettyPrinter",{".class":"AnyType","missing_import_name":null,"source_any":null,"type_of_any":1}],"bound_args":[],"def_extras":{"first_arg":"self"},"fallback":"builtins.function","from_concatenate":false,"implicit":true,"imprecise_arg_kinds":false,"is_ellipsis_args":false,"name":null,"ret_type":{".class":"AnyType","missing_import_name":null,"source_any":null,"type_of_any":1},"type_guard":null,"unpack_kwargs":false,"variables":[]}}},"_print_SeqPer":{".class":"SymbolTableNode","kind":"Mdef","node":{".class":"Var","flags":["is_initialized_in_class","is_inferred","has_explicit_value"],"fullname":"sympy.printing.pretty.pretty.PrettyPrinter._print_SeqPer","name":"_print_SeqPer","type":{".class":"CallableType","arg_kinds":[0,0],"arg_names":["self","s"],"arg_types":["sympy.printing.pretty.pretty.PrettyPrinter",{".class":"AnyType","missing_import_name":null,"source_any":null,"type_of_any":1}],"bound_args":[],"def_extras":{"first_arg":"self"},"fallback":"builtins.function","from_concatenate":false,"implicit":true,"imprecise_arg_kinds":false,"is_ellipsis_args":false,"name":null,"ret_type":{".class":"AnyType","missing_import_name":null,"source_any":null,"type_of_any":1},"type_guard":null,"unpack_kwargs":false,"variables":[]}}},"_print_Series":{".class":"SymbolTableNode","kind":"Mdef","node":{".class":"FuncDef","abstract_status":0,"arg_kinds":[0,0],"arg_names":["self","expr"],"dataclass_transform_spec":null,"flags":[],"fullname":"sympy.printing.pretty.pretty.PrettyPrinter._print_Series","name":"_print_Series","type":null}},"_print_SetExpr":{".class":"SymbolTableNode","kind":"Mdef","node":{".class":"FuncDef","abstract_status":0,"arg_kinds":[0,0],"arg_names":["self","se"],"dataclass_transform_spec":null,"flags":[],"fullname":"sympy.printing.pretty.pretty.PrettyPrinter._print_SetExpr","name":"_print_SetExpr","type":null}},"_print_SingularityFunction":{".class":"SymbolTableNode","kind":"Mdef","node":{".class":"FuncDef","abstract_status":0,"arg_kinds":[0,0],"arg_names":["self","e"],"dataclass_transform_spec":null,"flags":[],"fullname":"sympy.printing.pretty.pretty.PrettyPrinter._print_SingularityFunction","name":"_print_SingularityFunction","type":null}},"_print_Str":{".class":"SymbolTableNode","kind":"Mdef","node":{".class":"FuncDef","abstract_status":0,"arg_kinds":[0,0],"arg_names":["self","s"],"dataclass_transform_spec":null,"flags":[],"fullname":"sympy.printing.pretty.pretty.PrettyPrinter._print_Str","name":"_print_Str","type":null}},"_print_SubModule":{".class":"SymbolTableNode","kind":"Mdef","node":{".class":"FuncDef","abstract_status":0,"arg_kinds":[0,0],"arg_names":["self","M"],"dataclass_transform_spec":null,"flags":[],"fullname":"sympy.printing.pretty.pretty.PrettyPrinter._print_SubModule","name":"_print_SubModule","type":null}},"_print_Subs":{".class":"SymbolTableNode","kind":"Mdef","node":{".class":"FuncDef","abstract_status":0,"arg_kinds":[0,0],"arg_names":["self","e"],"dataclass_transform_spec":null,"flags":[],"fullname":"sympy.printing.pretty.pretty.PrettyPrinter._print_Subs","name":"_print_Subs","type":null}},"_print_Sum":{".class":"SymbolTableNode","kind":"Mdef","node":{".class":"FuncDef","abstract_status":0,"arg_kinds":[0,0],"arg_names":["self","expr"],"dataclass_transform_spec":null,"flags":[],"fullname":"sympy.printing.pretty.pretty.PrettyPrinter._print_Sum","name":"_print_Sum","type":null}},"_print_Symbol":{".class":"SymbolTableNode","kind":"Mdef","node":{".class":"FuncDef","abstract_status":0,"arg_kinds":[0,0,1],"arg_names":["self","e","bold_name"],"dataclass_transform_spec":null,"flags":[],"fullname":"sympy.printing.pretty.pretty.PrettyPrinter._print_Symbol","name":"_print_Symbol","type":null}},"_print_SymmetricDifference":{".class":"SymbolTableNode","kind":"Mdef","node":{".class":"FuncDef","abstract_status":0,"arg_kinds":[0,0],"arg_names":["self","u"],"dataclass_transform_spec":null,"flags":[],"fullname":"sympy.printing.pretty.pretty.PrettyPrinter._print_SymmetricDifference","name":"_print_SymmetricDifference","type":null}},"_print_TensAdd":{".class":"SymbolTableNode","kind":"Mdef","node":{".class":"FuncDef","abstract_status":0,"arg_kinds":[0,0],"arg_names":["self","expr"],"dataclass_transform_spec":null,"flags":[],"fullname":"sympy.printing.pretty.pretty.PrettyPrinter._print_TensAdd","name":"_print_TensAdd","type":null}},"_print_TensMul":{".class":"SymbolTableNode","kind":"Mdef","node":{".class":"FuncDef","abstract_status":0,"arg_kinds":[0,0],"arg_names":["self","expr"],"dataclass_transform_spec":null,"flags":[],"fullname":"sympy.printing.pretty.pretty.PrettyPrinter._print_TensMul","name":"_print_TensMul","type":null}},"_print_Tensor":{".class":"SymbolTableNode","kind":"Mdef","node":{".class":"FuncDef","abstract_status":0,"arg_kinds":[0,0],"arg_names":["self","expr"],"dataclass_transform_spec":null,"flags":[],"fullname":"sympy.printing.pretty.pretty.PrettyPrinter._print_Tensor","name":"_print_Tensor","type":null}},"_print_TensorElement":{".class":"SymbolTableNode","kind":"Mdef","node":{".class":"FuncDef","abstract_status":0,"arg_kinds":[0,0],"arg_names":["self","expr"],"dataclass_transform_spec":null,"flags":[],"fullname":"sympy.printing.pretty.pretty.PrettyPrinter._print_TensorElement","name":"_print_TensorElement","type":null}},"_print_TensorIndex":{".class":"SymbolTableNode","kind":"Mdef","node":{".class":"FuncDef","abstract_status":0,"arg_kinds":[0,0],"arg_names":["self","expr"],"dataclass_transform_spec":null,"flags":[],"fullname":"sympy.printing.pretty.pretty.PrettyPrinter._print_TensorIndex","name":"_print_TensorIndex","type":null}},"_print_TensorProduct":{".class":"SymbolTableNode","kind":"Mdef","node":{".class":"FuncDef","abstract_status":0,"arg_kinds":[0,0],"arg_names":["self","expr"],"dataclass_transform_spec":null,"flags":[],"fullname":"sympy.printing.pretty.pretty.PrettyPrinter._print_TensorProduct","name":"_print_TensorProduct","type":null}},"_print_Tr":{".class":"SymbolTableNode","kind":"Mdef","node":{".class":"FuncDef","abstract_status":0,"arg_kinds":[0,0],"arg_names":["self","p"],"dataclass_transform_spec":null,"flags":[],"fullname":"sympy.printing.pretty.pretty.PrettyPrinter._print_Tr","name":"_print_Tr","type":null}},"_print_Trace":{".class":"SymbolTableNode","kind":"Mdef","node":{".class":"FuncDef","abstract_status":0,"arg_kinds":[0,0],"arg_names":["self","e"],"dataclass_transform_spec":null,"flags":[],"fullname":"sympy.printing.pretty.pretty.PrettyPrinter._print_Trace","name":"_print_Trace","type":null}},"_print_TransferFunction":{".class":"SymbolTableNode","kind":"Mdef","node":{".class":"FuncDef","abstract_status":0,"arg_kinds":[0,0],"arg_names":["self","expr"],"dataclass_transform_spec":null,"flags":[],"fullname":"sympy.printing.pretty.pretty.PrettyPrinter._print_TransferFunction","name":"_print_TransferFunction","type":null}},"_print_TransferFunctionMatrix":{".class":"SymbolTableNode","kind":"Mdef","node":{".class":"FuncDef","abstract_status":0,"arg_kinds":[0,0],"arg_names":["self","expr"],"dataclass_transform_spec":null,"flags":[],"fullname":"sympy.printing.pretty.pretty.PrettyPrinter._print_TransferFunctionMatrix","name":"_print_TransferFunctionMatrix","type":null}},"_print_Transpose":{".class":"SymbolTableNode","kind":"Mdef","node":{".class":"FuncDef","abstract_status":0,"arg_kinds":[0,0],"arg_names":["self","expr"],"dataclass_transform_spec":null,"flags":[],"fullname":"sympy.printing.pretty.pretty.PrettyPrinter._print_Transpose","name":"_print_Transpose","type":null}},"_print_Tuple":{".class":"SymbolTableNode","kind":"Mdef","node":{".class":"FuncDef","abstract_status":0,"arg_kinds":[0,0],"arg_names":["self","expr"],"dataclass_transform_spec":null,"flags":[],"fullname":"sympy.printing.pretty.pretty.PrettyPrinter._print_Tuple","name":"_print_Tuple","type":null}},"_print_UnevaluatedExpr":{".class":"SymbolTableNode","kind":"Mdef","node":{".class":"FuncDef","abstract_status":0,"arg_kinds":[0,0],"arg_names":["self","expr"],"dataclass_transform_spec":null,"flags":[],"fullname":"sympy.printing.pretty.pretty.PrettyPrinter._print_UnevaluatedExpr","name":"_print_UnevaluatedExpr","type":null}},"_print_Union":{".class":"SymbolTableNode","kind":"Mdef","node":{".class":"FuncDef","abstract_status":0,"arg_kinds":[0,0],"arg_names":["self","u"],"dataclass_transform_spec":null,"flags":[],"fullname":"sympy.printing.pretty.pretty.PrettyPrinter._print_Union","name":"_print_Union","type":null}},"_print_UniversalSet":{".class":"SymbolTableNode","kind":"Mdef","node":{".class":"FuncDef","abstract_status":0,"arg_kinds":[0,0],"arg_names":["self","s"],"dataclass_transform_spec":null,"flags":[],"fullname":"sympy.printing.pretty.pretty.PrettyPrinter._print_UniversalSet","name":"_print_UniversalSet","type":null}},"_print_Variance":{".class":"SymbolTableNode","kind":"Mdef","node":{".class":"FuncDef","abstract_status":0,"arg_kinds":[0,0],"arg_names":["self","e"],"dataclass_transform_spec":null,"flags":[],"fullname":"sympy.printing.pretty.pretty.PrettyPrinter._print_Variance","name":"_print_Variance","type":null}},"_print_WedgeProduct":{".class":"SymbolTableNode","kind":"Mdef","node":{".class":"FuncDef","abstract_status":0,"arg_kinds":[0,0],"arg_names":["self","expr"],"dataclass_transform_spec":null,"flags":[],"fullname":"sympy.printing.pretty.pretty.PrettyPrinter._print_WedgeProduct","name":"_print_WedgeProduct","type":null}},"_print_Xor":{".class":"SymbolTableNode","kind":"Mdef","node":{".class":"FuncDef","abstract_status":0,"arg_kinds":[0,0],"arg_names":["self","e"],"dataclass_transform_spec":null,"flags":[],"fullname":"sympy.printing.pretty.pretty.PrettyPrinter._print_Xor","name":"_print_Xor","type":null}},"_print_ZeroMatrix":{".class":"SymbolTableNode","kind":"Mdef","node":{".class":"FuncDef","abstract_status":0,"arg_kinds":[0,0],"arg_names":["self","expr"],"dataclass_transform_spec":null,"flags":[],"fullname":"sympy.printing.pretty.pretty.PrettyPrinter._print_ZeroMatrix","name":"_print_ZeroMatrix","type":null}},"_print_airyai":{".class":"SymbolTableNode","kind":"Mdef","node":{".class":"FuncDef","abstract_status":0,"arg_kinds":[0,0],"arg_names":["self","e"],"dataclass_transform_spec":null,"flags":[],"fullname":"sympy.printing.pretty.pretty.PrettyPrinter._print_airyai","name":"_print_airyai","type":null}},"_print_airyaiprime":{".class":"SymbolTableNode","kind":"Mdef","node":{".class":"FuncDef","abstract_status":0,"arg_kinds":[0,0],"arg_names":["self","e"],"dataclass_transform_spec":null,"flags":[],"fullname":"sympy.printing.pretty.pretty.PrettyPrinter._print_airyaiprime","name":"_print_airyaiprime","type":null}},"_print_airybi":{".class":"SymbolTableNode","kind":"Mdef","node":{".class":"FuncDef","abstract_status":0,"arg_kinds":[0,0],"arg_names":["self","e"],"dataclass_transform_spec":null,"flags":[],"fullname":"sympy.printing.pretty.pretty.PrettyPrinter._print_airybi","name":"_print_airybi","type":null}},"_print_airybiprime":{".class":"SymbolTableNode","kind":"Mdef","node":{".class":"FuncDef","abstract_status":0,"arg_kinds":[0,0],"arg_names":["self","e"],"dataclass_transform_spec":null,"flags":[],"fullname":"sympy.printing.pretty.pretty.PrettyPrinter._print_airybiprime","name":"_print_airybiprime","type":null}},"_print_atan2":{".class":"SymbolTableNode","kind":"Mdef","node":{".class":"FuncDef","abstract_status":0,"arg_kinds":[0,0],"arg_names":["self","e"],"dataclass_transform_spec":null,"flags":[],"fullname":"sympy.printing.pretty.pretty.PrettyPrinter._print_atan2","name":"_print_atan2","type":null}},"_print_basestring":{".class":"SymbolTableNode","kind":"Mdef","node":{".class":"FuncDef","abstract_status":0,"arg_kinds":[0,0],"arg_names":["self","e"],"dataclass_transform_spec":null,"flags":[],"fullname":"sympy.printing.pretty.pretty.PrettyPrinter._print_basestring","name":"_print_basestring","type":null}},"_print_bell":{".class":"SymbolTableNode","kind":"Mdef","node":{".class":"Var","flags":["is_initialized_in_class","is_inferred","has_explicit_value"],"fullname":"sympy.printing.pretty.pretty.PrettyPrinter._print_bell","name":"_print_bell","type":{".class":"CallableType","arg_kinds":[0,0],"arg_names":["self","e"],"arg_types":["sympy.printing.pretty.pretty.PrettyPrinter",{".class":"AnyType","missing_import_name":null,"source_any":null,"type_of_any":1}],"bound_args":[],"def_extras":{"first_arg":"self"},"fallback":"builtins.function","from_concatenate":false,"implicit":true,"imprecise_arg_kinds":false,"is_ellipsis_args":false,"name":null,"ret_type":{".class":"AnyType","missing_import_name":null,"source_any":null,"type_of_any":1},"type_guard":null,"unpack_kwargs":false,"variables":[]}}},"_print_bernoulli":{".class":"SymbolTableNode","kind":"Mdef","node":{".class":"FuncDef","abstract_status":0,"arg_kinds":[0,0],"arg_names":["self","e"],"dataclass_transform_spec":null,"flags":[],"fullname":"sympy.printing.pretty.pretty.PrettyPrinter._print_bernoulli","name":"_print_bernoulli","type":null}},"_print_beta":{".class":"SymbolTableNode","kind":"Mdef","node":{".class":"FuncDef","abstract_status":0,"arg_kinds":[0,0],"arg_names":["self","e"],"dataclass_transform_spec":null,"flags":[],"fullname":"sympy.printing.pretty.pretty.PrettyPrinter._print_beta","name":"_print_beta","type":null}},"_print_betainc":{".class":"SymbolTableNode","kind":"Mdef","node":{".class":"FuncDef","abstract_status":0,"arg_kinds":[0,0],"arg_names":["self","e"],"dataclass_transform_spec":null,"flags":[],"fullname":"sympy.printing.pretty.pretty.PrettyPrinter._print_betainc","name":"_print_betainc","type":null}},"_print_betainc_regularized":{".class":"SymbolTableNode","kind":"Mdef","node":{".class":"FuncDef","abstract_status":0,"arg_kinds":[0,0],"arg_names":["self","e"],"dataclass_transform_spec":null,"flags":[],"fullname":"sympy.printing.pretty.pretty.PrettyPrinter._print_betainc_regularized","name":"_print_betainc_regularized","type":null}},"_print_binomial":{".class":"SymbolTableNode","kind":"Mdef","node":{".class":"FuncDef","abstract_status":0,"arg_kinds":[0,0],"arg_names":["self","e"],"dataclass_transform_spec":null,"flags":[],"fullname":"sympy.printing.pretty.pretty.PrettyPrinter._print_binomial","name":"_print_binomial","type":null}},"_print_catalan":{".class":"SymbolTableNode","kind":"Mdef","node":{".class":"FuncDef","abstract_status":0,"arg_kinds":[0,0],"arg_names":["self","e"],"dataclass_transform_spec":null,"flags":[],"fullname":"sympy.printing.pretty.pretty.PrettyPrinter._print_catalan","name":"_print_catalan","type":null}},"_print_ceiling":{".class":"SymbolTableNode","kind":"Mdef","node":{".class":"FuncDef","abstract_status":0,"arg_kinds":[0,0],"arg_names":["self","e"],"dataclass_transform_spec":null,"flags":[],"fullname":"sympy.printing.pretty.pretty.PrettyPrinter._print_ceiling","name":"_print_ceiling","type":null}},"_print_conjugate":{".class":"SymbolTableNode","kind":"Mdef","node":{".class":"FuncDef","abstract_status":0,"arg_kinds":[0,0],"arg_names":["self","e"],"dataclass_transform_spec":null,"flags":[],"fullname":"sympy.printing.pretty.pretty.PrettyPrinter._print_conjugate","name":"_print_conjugate","type":null}},"_print_dict":{".class":"SymbolTableNode","kind":"Mdef","node":{".class":"FuncDef","abstract_status":0,"arg_kinds":[0,0],"arg_names":["self","d"],"dataclass_transform_spec":null,"flags":[],"fullname":"sympy.printing.pretty.pretty.PrettyPrinter._print_dict","name":"_print_dict","type":null}},"_print_dirichlet_eta":{".class":"SymbolTableNode","kind":"Mdef","node":{".class":"FuncDef","abstract_status":0,"arg_kinds":[0,0],"arg_names":["self","e"],"dataclass_transform_spec":null,"flags":[],"fullname":"sympy.printing.pretty.pretty.PrettyPrinter._print_dirichlet_eta","name":"_print_dirichlet_eta","type":null}},"_print_elliptic_e":{".class":"SymbolTableNode","kind":"Mdef","node":{".class":"FuncDef","abstract_status":0,"arg_kinds":[0,0],"arg_names":["self","e"],"dataclass_transform_spec":null,"flags":[],"fullname":"sympy.printing.pretty.pretty.PrettyPrinter._print_elliptic_e","name":"_print_elliptic_e","type":null}},"_print_elliptic_f":{".class":"SymbolTableNode","kind":"Mdef","node":{".class":"FuncDef","abstract_status":0,"arg_kinds":[0,0],"arg_names":["self","e"],"dataclass_transform_spec":null,"flags":[],"fullname":"sympy.printing.pretty.pretty.PrettyPrinter._print_elliptic_f","name":"_print_elliptic_f","type":null}},"_print_elliptic_k":{".class":"SymbolTableNode","kind":"Mdef","node":{".class":"FuncDef","abstract_status":0,"arg_kinds":[0,0],"arg_names":["self","e"],"dataclass_transform_spec":null,"flags":[],"fullname":"sympy.printing.pretty.pretty.PrettyPrinter._print_elliptic_k","name":"_print_elliptic_k","type":null}},"_print_elliptic_pi":{".class":"SymbolTableNode","kind":"Mdef","node":{".class":"FuncDef","abstract_status":0,"arg_kinds":[0,0],"arg_names":["self","e"],"dataclass_transform_spec":null,"flags":[],"fullname":"sympy.printing.pretty.pretty.PrettyPrinter._print_elliptic_pi","name":"_print_elliptic_pi","type":null}},"_print_euler":{".class":"SymbolTableNode","kind":"Mdef","node":{".class":"FuncDef","abstract_status":0,"arg_kinds":[0,0],"arg_names":["self","e"],"dataclass_transform_spec":null,"flags":[],"fullname":"sympy.printing.pretty.pretty.PrettyPrinter._print_euler","name":"_print_euler","type":null}},"_print_expint":{".class":"SymbolTableNode","kind":"Mdef","node":{".class":"FuncDef","abstract_status":0,"arg_kinds":[0,0],"arg_names":["self","e"],"dataclass_transform_spec":null,"flags":[],"fullname":"sympy.printing.pretty.pretty.PrettyPrinter._print_expint","name":"_print_expint","type":null}},"_print_factorial":{".class":"SymbolTableNode","kind":"Mdef","node":{".class":"FuncDef","abstract_status":0,"arg_kinds":[0,0],"arg_names":["self","e"],"dataclass_transform_spec":null,"flags":[],"fullname":"sympy.printing.pretty.pretty.PrettyPrinter._print_factorial","name":"_print_factorial","type":null}},"_print_factorial2":{".class":"SymbolTableNode","kind":"Mdef","node":{".class":"FuncDef","abstract_status":0,"arg_kinds":[0,0],"arg_names":["self","e"],"dataclass_transform_spec":null,"flags":[],"fullname":"sympy.printing.pretty.pretty.PrettyPrinter._print_factorial2","name":"_print_factorial2","type":null}},"_print_fibonacci":{".class":"SymbolTableNode","kind":"Mdef","node":{".class":"FuncDef","abstract_status":0,"arg_kinds":[0,0],"arg_names":["self","e"],"dataclass_transform_spec":null,"flags":[],"fullname":"sympy.printing.pretty.pretty.PrettyPrinter._print_fibonacci","name":"_print_fibonacci","type":null}},"_print_floor":{".class":"SymbolTableNode","kind":"Mdef","node":{".class":"FuncDef","abstract_status":0,"arg_kinds":[0,0],"arg_names":["self","e"],"dataclass_transform_spec":null,"flags":[],"fullname":"sympy.printing.pretty.pretty.PrettyPrinter._print_floor","name":"_print_floor","type":null}},"_print_fresnelc":{".class":"SymbolTableNode","kind":"Mdef","node":{".class":"FuncDef","abstract_status":0,"arg_kinds":[0,0],"arg_names":["self","e"],"dataclass_transform_spec":null,"flags":[],"fullname":"sympy.printing.pretty.pretty.PrettyPrinter._print_fresnelc","name":"_print_fresnelc","type":null}},"_print_fresnels":{".class":"SymbolTableNode","kind":"Mdef","node":{".class":"FuncDef","abstract_status":0,"arg_kinds":[0,0],"arg_names":["self","e"],"dataclass_transform_spec":null,"flags":[],"fullname":"sympy.printing.pretty.pretty.PrettyPrinter._print_fresnels","name":"_print_fresnels","type":null}},"_print_frozenset":{".class":"SymbolTableNode","kind":"Mdef","node":{".class":"FuncDef","abstract_status":0,"arg_kinds":[0,0],"arg_names":["self","s"],"dataclass_transform_spec":null,"flags":[],"fullname":"sympy.printing.pretty.pretty.PrettyPrinter._print_frozenset","name":"_print_frozenset","type":null}},"_print_gamma":{".class":"SymbolTableNode","kind":"Mdef","node":{".class":"FuncDef","abstract_status":0,"arg_kinds":[0,0],"arg_names":["self","e"],"dataclass_transform_spec":null,"flags":[],"fullname":"sympy.printing.pretty.pretty.PrettyPrinter._print_gamma","name":"_print_gamma","type":null}},"_print_hyper":{".class":"SymbolTableNode","kind":"Mdef","node":{".class":"FuncDef","abstract_status":0,"arg_kinds":[0,0],"arg_names":["self","e"],"dataclass_transform_spec":null,"flags":[],"fullname":"sympy.printing.pretty.pretty.PrettyPrinter._print_hyper","name":"_print_hyper","type":null}},"_print_lerchphi":{".class":"SymbolTableNode","kind":"Mdef","node":{".class":"FuncDef","abstract_status":0,"arg_kinds":[0,0],"arg_names":["self","e"],"dataclass_transform_spec":null,"flags":[],"fullname":"sympy.printing.pretty.pretty.PrettyPrinter._print_lerchphi","name":"_print_lerchphi","type":null}},"_print_list":{".class":"SymbolTableNode","kind":"Mdef","node":{".class":"FuncDef","abstract_status":0,"arg_kinds":[0,0],"arg_names":["self","l"],"dataclass_transform_spec":null,"flags":[],"fullname":"sympy.printing.pretty.pretty.PrettyPrinter._print_list","name":"_print_list","type":null}},"_print_lowergamma":{".class":"SymbolTableNode","kind":"Mdef","node":{".class":"FuncDef","abstract_status":0,"arg_kinds":[0,0],"arg_names":["self","e"],"dataclass_transform_spec":null,"flags":[],"fullname":"sympy.printing.pretty.pretty.PrettyPrinter._print_lowergamma","name":"_print_lowergamma","type":null}},"_print_lucas":{".class":"SymbolTableNode","kind":"Mdef","node":{".class":"FuncDef","abstract_status":0,"arg_kinds":[0,0],"arg_names":["self","e"],"dataclass_transform_spec":null,"flags":[],"fullname":"sympy.printing.pretty.pretty.PrettyPrinter._print_lucas","name":"_print_lucas","type":null}},"_print_mathieuc":{".class":"SymbolTableNode","kind":"Mdef","node":{".class":"FuncDef","abstract_status":0,"arg_kinds":[0,0],"arg_names":["self","e"],"dataclass_transform_spec":null,"flags":[],"fullname":"sympy.printing.pretty.pretty.PrettyPrinter._print_mathieuc","name":"_print_mathieuc","type":null}},"_print_mathieucprime":{".class":"SymbolTableNode","kind":"Mdef","node":{".class":"FuncDef","abstract_status":0,"arg_kinds":[0,0],"arg_names":["self","e"],"dataclass_transform_spec":null,"flags":[],"fullname":"sympy.printing.pretty.pretty.PrettyPrinter._print_mathieucprime","name":"_print_mathieucprime","type":null}},"_print_mathieus":{".class":"SymbolTableNode","kind":"Mdef","node":{".class":"FuncDef","abstract_status":0,"arg_kinds":[0,0],"arg_names":["self","e"],"dataclass_transform_spec":null,"flags":[],"fullname":"sympy.printing.pretty.pretty.PrettyPrinter._print_mathieus","name":"_print_mathieus","type":null}},"_print_mathieusprime":{".class":"SymbolTableNode","kind":"Mdef","node":{".class":"FuncDef","abstract_status":0,"arg_kinds":[0,0],"arg_names":["self","e"],"dataclass_transform_spec":null,"flags":[],"fullname":"sympy.printing.pretty.pretty.PrettyPrinter._print_mathieusprime","name":"_print_mathieusprime","type":null}},"_print_matrix_contents":{".class":"SymbolTableNode","kind":"Mdef","node":{".class":"FuncDef","abstract_status":0,"arg_kinds":[0,0],"arg_names":["self","e"],"dataclass_transform_spec":null,"flags":[],"fullname":"sympy.printing.pretty.pretty.PrettyPrinter._print_matrix_contents","name":"_print_matrix_contents","type":null}},"_print_meijerg":{".class":"SymbolTableNode","kind":"Mdef","node":{".class":"FuncDef","abstract_status":0,"arg_kinds":[0,0],"arg_names":["self","e"],"dataclass_transform_spec":null,"flags":[],"fullname":"sympy.printing.pretty.pretty.PrettyPrinter._print_meijerg","name":"_print_meijerg","type":null}},"_print_nth_root":{".class":"SymbolTableNode","kind":"Mdef","node":{".class":"FuncDef","abstract_status":0,"arg_kinds":[0,0,0],"arg_names":["self","base","root"],"dataclass_transform_spec":null,"flags":[],"fullname":"sympy.printing.pretty.pretty.PrettyPrinter._print_nth_root","name":"_print_nth_root","type":null}},"_print_number_function":{".class":"SymbolTableNode","kind":"Mdef","node":{".class":"FuncDef","abstract_status":0,"arg_kinds":[0,0,0],"arg_names":["self","e","name"],"dataclass_transform_spec":null,"flags":[],"fullname":"sympy.printing.pretty.pretty.PrettyPrinter._print_number_function","name":"_print_number_function","type":null}},"_print_primenu":{".class":"SymbolTableNode","kind":"Mdef","node":{".class":"FuncDef","abstract_status":0,"arg_kinds":[0,0],"arg_names":["self","e"],"dataclass_transform_spec":null,"flags":[],"fullname":"sympy.printing.pretty.pretty.PrettyPrinter._print_primenu","name":"_print_primenu","type":null}},"_print_primeomega":{".class":"SymbolTableNode","kind":"Mdef","node":{".class":"FuncDef","abstract_status":0,"arg_kinds":[0,0],"arg_names":["self","e"],"dataclass_transform_spec":null,"flags":[],"fullname":"sympy.printing.pretty.pretty.PrettyPrinter._print_primeomega","name":"_print_primeomega","type":null}},"_print_seq":{".class":"SymbolTableNode","kind":"Mdef","node":{".class":"FuncDef","abstract_status":0,"arg_kinds":[0,0,1,1,1,1,1],"arg_names":["self","seq","left","right","delimiter","parenthesize","ifascii_nougly"],"dataclass_transform_spec":null,"flags":[],"fullname":"sympy.printing.pretty.pretty.PrettyPrinter._print_seq","name":"_print_seq","type":null}},"_print_set":{".class":"SymbolTableNode","kind":"Mdef","node":{".class":"FuncDef","abstract_status":0,"arg_kinds":[0,0],"arg_names":["self","s"],"dataclass_transform_spec":null,"flags":[],"fullname":"sympy.printing.pretty.pretty.PrettyPrinter._print_set","name":"_print_set","type":null}},"_print_stieltjes":{".class":"SymbolTableNode","kind":"Mdef","node":{".class":"FuncDef","abstract_status":0,"arg_kinds":[0,0],"arg_names":["self","e"],"dataclass_transform_spec":null,"flags":[],"fullname":"sympy.printing.pretty.pretty.PrettyPrinter._print_stieltjes","name":"_print_stieltjes","type":null}},"_print_stringPict":{".class":"SymbolTableNode","kind":"Mdef","node":{".class":"FuncDef","abstract_status":0,"arg_kinds":[0,0],"arg_names":["self","e"],"dataclass_transform_spec":null,"flags":[],"fullname":"sympy.printing.pretty.pretty.PrettyPrinter._print_stringPict","name":"_print_stringPict","type":null}},"_print_subfactorial":{".class":"SymbolTableNode","kind":"Mdef","node":{".class":"FuncDef","abstract_status":0,"arg_kinds":[0,0],"arg_names":["self","e"],"dataclass_transform_spec":null,"flags":[],"fullname":"sympy.printing.pretty.pretty.PrettyPrinter._print_subfactorial","name":"_print_subfactorial","type":null}},"_print_tribonacci":{".class":"SymbolTableNode","kind":"Mdef","node":{".class":"FuncDef","abstract_status":0,"arg_kinds":[0,0],"arg_names":["self","e"],"dataclass_transform_spec":null,"flags":[],"fullname":"sympy.printing.pretty.pretty.PrettyPrinter._print_tribonacci","name":"_print_tribonacci","type":null}},"_print_tuple":{".class":"SymbolTableNode","kind":"Mdef","node":{".class":"FuncDef","abstract_status":0,"arg_kinds":[0,0],"arg_names":["self","t"],"dataclass_transform_spec":null,"flags":[],"fullname":"sympy.printing.pretty.pretty.PrettyPrinter._print_tuple","name":"_print_tuple","type":null}},"_print_uppergamma":{".class":"SymbolTableNode","kind":"Mdef","node":{".class":"FuncDef","abstract_status":0,"arg_kinds":[0,0],"arg_names":["self","e"],"dataclass_transform_spec":null,"flags":[],"fullname":"sympy.printing.pretty.pretty.PrettyPrinter._print_uppergamma","name":"_print_uppergamma","type":null}},"_printer_tensor_indices":{".class":"SymbolTableNode","kind":"Mdef","node":{".class":"FuncDef","abstract_status":0,"arg_kinds":[0,0,0,1],"arg_names":["self","name","indices","index_map"],"dataclass_transform_spec":null,"flags":[],"fullname":"sympy.printing.pretty.pretty.PrettyPrinter._printer_tensor_indices","name":"_printer_tensor_indices","type":null}},"_special_function_classes":{".class":"SymbolTableNode","kind":"Mdef","node":{".class":"Decorator","func":{".class":"FuncDef","abstract_status":0,"arg_kinds":[0],"arg_names":["self"],"dataclass_transform_spec":null,"flags":["is_property","is_decorated"],"fullname":"sympy.printing.pretty.pretty.PrettyPrinter._special_function_classes","name":"_special_function_classes","type":null},"is_overload":false,"var":{".class":"Var","flags":["is_initialized_in_class","is_property","is_ready","is_inferred"],"fullname":"sympy.printing.pretty.pretty.PrettyPrinter._special_function_classes","name":"_special_function_classes","type":{".class":"CallableType","arg_kinds":[0],"arg_names":["self"],"arg_types":["sympy.printing.pretty.pretty.PrettyPrinter"],"bound_args":[],"def_extras":{"first_arg":"self"},"fallback":"builtins.function","from_concatenate":false,"implicit":true,"imprecise_arg_kinds":false,"is_ellipsis_args":false,"name":"_special_function_classes of PrettyPrinter","ret_type":{".class":"AnyType","missing_import_name":null,"source_any":null,"type_of_any":1},"type_guard":null,"unpack_kwargs":false,"variables":[]}}}},"_use_unicode":{".class":"SymbolTableNode","kind":"Mdef","node":{".class":"Decorator","func":{".class":"FuncDef","abstract_status":0,"arg_kinds":[0],"arg_names":["self"],"dataclass_transform_spec":null,"flags":["is_property","is_decorated"],"fullname":"sympy.printing.pretty.pretty.PrettyPrinter._use_unicode","name":"_use_unicode","type":null},"is_overload":false,"var":{".class":"Var","flags":["is_initialized_in_class","is_property","is_ready","is_inferred"],"fullname":"sympy.printing.pretty.pretty.PrettyPrinter._use_unicode","name":"_use_unicode","type":{".class":"CallableType","arg_kinds":[0],"arg_names":["self"],"arg_types":["sympy.printing.pretty.pretty.PrettyPrinter"],"bound_args":[],"def_extras":{"first_arg":"self"},"fallback":"builtins.function","from_concatenate":false,"implicit":true,"imprecise_arg_kinds":false,"is_ellipsis_args":false,"name":"_use_unicode of PrettyPrinter","ret_type":{".class":"AnyType","missing_import_name":null,"source_any":null,"type_of_any":1},"type_guard":null,"unpack_kwargs":false,"variables":[]}}}},"doprint":{".class":"SymbolTableNode","kind":"Mdef","node":{".class":"FuncDef","abstract_status":0,"arg_kinds":[0,0],"arg_names":["self","expr"],"dataclass_transform_spec":null,"flags":[],"fullname":"sympy.printing.pretty.pretty.PrettyPrinter.doprint","name":"doprint","type":null}},"emptyPrinter":{".class":"SymbolTableNode","kind":"Mdef","node":{".class":"FuncDef","abstract_status":0,"arg_kinds":[0,0],"arg_names":["self","expr"],"dataclass_transform_spec":null,"flags":[],"fullname":"sympy.printing.pretty.pretty.PrettyPrinter.emptyPrinter","name":"emptyPrinter","type":null}},"join":{".class":"SymbolTableNode","kind":"Mdef","node":{".class":"FuncDef","abstract_status":0,"arg_kinds":[0,0,0],"arg_names":["self","delimiter","args"],"dataclass_transform_spec":null,"flags":[],"fullname":"sympy.printing.pretty.pretty.PrettyPrinter.join","name":"join","type":null}},"printmethod":{".class":"SymbolTableNode","kind":"Mdef","node":{".class":"Var","flags":["is_initialized_in_class","is_inferred","has_explicit_value"],"fullname":"sympy.printing.pretty.pretty.PrettyPrinter.printmethod","name":"printmethod","type":"builtins.str"}}},"self_type":{".class":"TypeVarType","default":{".class":"AnyType","missing_import_name":null,"source_any":null,"type_of_any":4},"fullname":"sympy.printing.pretty.pretty.PrettyPrinter.Self","id":0,"name":"Self","namespace":"","upper_bound":"sympy.printing.pretty.pretty.PrettyPrinter","values":[],"variance":0},"slots":null,"tuple_type":null,"type_vars":[],"typeddict_type":null}},"Printer":{".class":"SymbolTableNode","cross_ref":"sympy.printing.printer.Printer","kind":"Gdef"},"Rational":{".class":"SymbolTableNode","cross_ref":"sympy.core.numbers.Rational","kind":"Gdef"},"S":{".class":"SymbolTableNode","cross_ref":"sympy.core.singleton.S","kind":"Gdef"},"Symbol":{".class":"SymbolTableNode","cross_ref":"sympy.core.symbol.Symbol","kind":"Gdef"},"SympifyError":{".class":"SymbolTableNode","cross_ref":"sympy.core.sympify.SympifyError","kind":"Gdef"},"Tuple":{".class":"SymbolTableNode","cross_ref":"sympy.core.containers.Tuple","kind":"Gdef"},"U":{".class":"SymbolTableNode","cross_ref":"sympy.printing.pretty.pretty_symbology.U","kind":"Gdef"},"__annotations__":{".class":"SymbolTableNode","kind":"Gdef","node":{".class":"Var","flags":["is_ready"],"fullname":"sympy.printing.pretty.pretty.__annotations__","name":"__annotations__","type":{".class":"Instance","args":["builtins.str",{".class":"AnyType","missing_import_name":null,"source_any":null,"type_of_any":6}],"type_ref":"builtins.dict"}}},"__doc__":{".class":"SymbolTableNode","kind":"Gdef","node":{".class":"Var","flags":["is_ready"],"fullname":"sympy.printing.pretty.pretty.__doc__","name":"__doc__","type":"builtins.str"}},"__file__":{".class":"SymbolTableNode","kind":"Gdef","node":{".class":"Var","flags":["is_ready"],"fullname":"sympy.printing.pretty.pretty.__file__","name":"__file__","type":"builtins.str"}},"__name__":{".class":"SymbolTableNode","kind":"Gdef","node":{".class":"Var","flags":["is_ready"],"fullname":"sympy.printing.pretty.pretty.__name__","name":"__name__","type":"builtins.str"}},"__package__":{".class":"SymbolTableNode","kind":"Gdef","node":{".class":"Var","flags":["is_ready"],"fullname":"sympy.printing.pretty.pretty.__package__","name":"__package__","type":"builtins.str"}},"annotated":{".class":"SymbolTableNode","cross_ref":"sympy.printing.pretty.pretty_symbology.annotated","kind":"Gdef"},"default_sort_key":{".class":"SymbolTableNode","cross_ref":"sympy.core.sorting.default_sort_key","kind":"Gdef"},"greek_unicode":{".class":"SymbolTableNode","cross_ref":"sympy.printing.pretty.pretty_symbology.greek_unicode","kind":"Gdef"},"has_variety":{".class":"SymbolTableNode","cross_ref":"sympy.utilities.iterables.has_variety","kind":"Gdef"},"hobj":{".class":"SymbolTableNode","cross_ref":"sympy.printing.pretty.pretty_symbology.hobj","kind":"Gdef"},"itertools":{".class":"SymbolTableNode","cross_ref":"itertools","kind":"Gdef"},"pager_print":{".class":"SymbolTableNode","kind":"Gdef","node":{".class":"FuncDef","abstract_status":0,"arg_kinds":[0,4],"arg_names":["expr","settings"],"dataclass_transform_spec":null,"flags":[],"fullname":"sympy.printing.pretty.pretty.pager_print","name":"pager_print","type":null}},"pprint":{".class":"SymbolTableNode","kind":"Gdef","node":{".class":"Var","flags":["is_inferred","has_explicit_value"],"fullname":"sympy.printing.pretty.pretty.pprint","name":"pprint","type":{".class":"CallableType","arg_kinds":[0,4],"arg_names":["expr","kwargs"],"arg_types":[{".class":"AnyType","missing_import_name":null,"source_any":null,"type_of_any":1},{".class":"AnyType","missing_import_name":null,"source_any":null,"type_of_any":1}],"bound_args":[],"def_extras":{"first_arg":null},"fallback":"builtins.function","from_concatenate":false,"implicit":true,"imprecise_arg_kinds":false,"is_ellipsis_args":false,"name":null,"ret_type":{".class":"AnyType","missing_import_name":null,"source_any":null,"type_of_any":1},"type_guard":null,"unpack_kwargs":false,"variables":[]}}},"pprint_try_use_unicode":{".class":"SymbolTableNode","kind":"Gdef","node":{".class":"Var","flags":["is_inferred","has_explicit_value"],"fullname":"sympy.printing.pretty.pretty.pprint_try_use_unicode","name":"pprint_try_use_unicode","type":{".class":"CallableType","arg_kinds":[],"arg_names":[],"arg_types":[],"bound_args":[],"def_extras":{"first_arg":null},"fallback":"builtins.function","from_concatenate":false,"implicit":true,"imprecise_arg_kinds":false,"is_ellipsis_args":false,"name":null,"ret_type":{".class":"AnyType","missing_import_name":null,"source_any":null,"type_of_any":1},"type_guard":null,"unpack_kwargs":false,"variables":[]}}},"pprint_use_unicode":{".class":"SymbolTableNode","kind":"Gdef","node":{".class":"Var","flags":["is_inferred","has_explicit_value"],"fullname":"sympy.printing.pretty.pretty.pprint_use_unicode","name":"pprint_use_unicode","type":{".class":"CallableType","arg_kinds":[1],"arg_names":["flag"],"arg_types":[{".class":"AnyType","missing_import_name":null,"source_any":null,"type_of_any":1}],"bound_args":[],"def_extras":{"first_arg":null},"fallback":"builtins.function","from_concatenate":false,"implicit":true,"imprecise_arg_kinds":false,"is_ellipsis_args":false,"name":null,"ret_type":{".class":"AnyType","missing_import_name":null,"source_any":null,"type_of_any":1},"type_guard":null,"unpack_kwargs":false,"variables":[]}}},"precedence":{".class":"SymbolTableNode","cross_ref":"sympy.printing.precedence.precedence","kind":"Gdef"},"precedence_traditional":{".class":"SymbolTableNode","cross_ref":"sympy.printing.precedence.precedence_traditional","kind":"Gdef"},"pretty":{".class":"SymbolTableNode","kind":"Gdef","node":{".class":"Decorator","func":{".class":"FuncDef","abstract_status":0,"arg_kinds":[0,4],"arg_names":["expr","settings"],"dataclass_transform_spec":null,"flags":["is_decorated"],"fullname":"sympy.printing.pretty.pretty.pretty","name":"pretty","type":null},"is_overload":false,"var":{".class":"Var","flags":["is_ready","is_inferred"],"fullname":"sympy.printing.pretty.pretty.pretty","name":"pretty","type":{".class":"AnyType","missing_import_name":null,"source_any":{".class":"AnyType","missing_import_name":null,"source_any":null,"type_of_any":1},"type_of_any":7}}}},"prettyForm":{".class":"SymbolTableNode","cross_ref":"sympy.printing.pretty.stringpict.prettyForm","kind":"Gdef"},"pretty_atom":{".class":"SymbolTableNode","cross_ref":"sympy.printing.pretty.pretty_symbology.pretty_atom","kind":"Gdef"},"pretty_print":{".class":"SymbolTableNode","kind":"Gdef","node":{".class":"FuncDef","abstract_status":0,"arg_kinds":[0,4],"arg_names":["expr","kwargs"],"dataclass_transform_spec":null,"flags":[],"fullname":"sympy.printing.pretty.pretty.pretty_print","name":"pretty_print","type":null}},"pretty_symbol":{".class":"SymbolTableNode","cross_ref":"sympy.printing.pretty.pretty_symbology.pretty_symbol","kind":"Gdef"},"pretty_try_use_unicode":{".class":"SymbolTableNode","cross_ref":"sympy.printing.pretty.pretty_symbology.pretty_try_use_unicode","kind":"Gdef"},"pretty_use_unicode":{".class":"SymbolTableNode","cross_ref":"sympy.printing.pretty.pretty_symbology.pretty_use_unicode","kind":"Gdef"},"print_function":{".class":"SymbolTableNode","cross_ref":"sympy.printing.printer.print_function","kind":"Gdef"},"requires_partial":{".class":"SymbolTableNode","cross_ref":"sympy.printing.conventions.requires_partial","kind":"Gdef"},"sstr":{".class":"SymbolTableNode","cross_ref":"sympy.printing.str.sstr","kind":"Gdef"},"stringPict":{".class":"SymbolTableNode","cross_ref":"sympy.printing.pretty.stringpict.stringPict","kind":"Gdef"},"sympy_deprecation_warning":{".class":"SymbolTableNode","cross_ref":"sympy.utilities.exceptions.sympy_deprecation_warning","kind":"Gdef"},"vobj":{".class":"SymbolTableNode","cross_ref":"sympy.printing.pretty.pretty_symbology.vobj","kind":"Gdef"},"xobj":{".class":"SymbolTableNode","cross_ref":"sympy.printing.pretty.pretty_symbology.xobj","kind":"Gdef"},"xsym":{".class":"SymbolTableNode","cross_ref":"sympy.printing.pretty.pretty_symbology.xsym","kind":"Gdef"}},"path":"/root/miniconda3/envs/dc/lib/python3.11/site-packages/sympy/printing/pretty/pretty.py"}